{"2024-02-07-2024-02-07": {"MEX - Influenciadores de Interés 2 - TW": [{"valor": 3, "palabra": "primera-atentado-izquierdo"}, {"valor": 3, "palabra": "atentado-izquierdo-colaborador"}, {"valor": 3, "palabra": "presidente-andrés-manuel"}, {"valor": 3, "palabra": "andrés-manuel-obrador"}, {"valor": 2, "palabra": "ciudad-méxico-materia"}, {"valor": 2, "palabra": "méxico-materia-movilidad"}, {"valor": 2, "palabra": "materia-movilidad-contamos"}, {"valor": 2, "palabra": "movilidad-contamos-transporte"}, {"valor": 2, "palabra": "contamos-transporte-público"}, {"valor": 2, "palabra": "transporte-público-económico"}, {"valor": 2, "palabra": "público-económico-moderno"}, {"valor": 2, "palabra": "económico-moderno-movilidad"}, {"valor": 2, "palabra": "moderno-movilidad-complicadas"}, {"valor": 2, "palabra": "movilidad-complicadas-ciudad"}, {"valor": 2, "palabra": "complicadas-ciudad-reconfigura"}, {"valor": 2, "palabra": "ciudad-reconfigura-conformación"}, {"valor": 2, "palabra": "reconfigura-conformación-empresa"}, {"valor": 2, "palabra": "conformación-empresa-movilidad"}, {"valor": 2, "palabra": "empresa-movilidad-noroeste"}, {"valor": 2, "palabra": "movilidad-noroeste-operación"}, {"valor": 2, "palabra": "noroeste-operación-nuevas"}, {"valor": 2, "palabra": "operación-nuevas-unidades"}, {"valor": 2, "palabra": "nuevas-unidades-seguras"}, {"valor": 2, "palabra": "unidades-seguras-cómodas"}, {"valor": 2, "palabra": "seguras-cómodas-equipadas"}, {"valor": 2, "palabra": "cómodas-equipadas-acciones"}, {"valor": 2, "palabra": "equipadas-acciones-beneficiamos"}, {"valor": 2, "palabra": "acciones-beneficiamos-usuarios"}, {"valor": 2, "palabra": "beneficiamos-usuarios-trabajadores"}, {"valor": 2, "palabra": "usuarios-trabajadores-ambiente"}], "MEX - Influenciadores de Interés - TW": [{"valor": 3, "palabra": "violencia-política-género"}, {"valor": 3, "palabra": "𝗖𝗼𝗹𝗼𝗻𝗶𝗮-𝗕𝗮𝗿𝗿𝗼𝘀-𝗦𝗶𝗲𝗿𝗿𝗮"}, {"valor": 2, "palabra": "sandra-cuevas-muñecas"}, {"valor": 2, "palabra": "cuevas-muñecas-sandra"}, {"valor": 2, "palabra": "febrero-entrevista-germán"}, {"valor": 2, "palabra": "entrevista-germán-martínez"}, {"valor": 2, "palabra": "germán-martínez-analizar"}, {"valor": 2, "palabra": "martínez-analizar-iniciativas"}, {"valor": 2, "palabra": "analizar-iniciativas-sorprende"}, {"valor": 2, "palabra": "iniciativas-sorprende-música"}, {"valor": 2, "palabra": "sorprende-música-enfrentan"}, {"valor": 2, "palabra": "música-enfrentan-aficionados"}, {"valor": 2, "palabra": "enfrentan-aficionados-monterrey"}, {"valor": 2, "palabra": "aficionados-monterrey-comunicaciones"}, {"valor": 2, "palabra": "honores-nuestro-lábaro"}, {"valor": 2, "palabra": "nuestro-lábaro-patrio"}, {"valor": 2, "palabra": "lábaro-patrio-conmemoración"}, {"valor": 2, "palabra": "patrio-conmemoración-aniversario"}, {"valor": 2, "palabra": "conmemoración-aniversario-constitución"}, {"valor": 2, "palabra": "entrevista-cárdenas-explicó"}, {"valor": 1, "palabra": "amigos-pejistas-adueñó"}, {"valor": 1, "palabra": "pejistas-adueñó-conversación"}, {"valor": 1, "palabra": "adueñó-conversación-pública"}, {"valor": 1, "palabra": "conversación-pública-iniciativas"}, {"valor": 1, "palabra": "pública-iniciativas-constitucionales"}, {"valor": 1, "palabra": "iniciativas-constitucionales-siendo"}, {"valor": 1, "palabra": "constitucionales-siendo-genuina"}, {"valor": 1, "palabra": "siendo-genuina-doctor"}, {"valor": 1, "palabra": "genuina-doctor-leonardo"}, {"valor": 1, "palabra": "doctor-leonardo-curzio"}], "MEX - Medios CDMX - TW": [{"valor": 11, "palabra": "presidente-andrés-manuel"}, {"valor": 10, "palabra": "expresidente-sebastián-piñera"}, {"valor": 9, "palabra": "andrés-manuel-obrador"}, {"valor": 8, "palabra": "puñado-valientes-conquistó"}, {"valor": 8, "palabra": "valientes-conquistó-independencia"}, {"valor": 8, "palabra": "conquistó-independencia-reforma"}, {"valor": 8, "palabra": "independencia-reforma-revolución"}, {"valor": 8, "palabra": "reforma-revolución-podemos"}, {"valor": 8, "palabra": "revolución-podemos-lograrlo"}, {"valor": 8, "palabra": "podemos-lograrlo-disparar"}, {"valor": 8, "palabra": "lograrlo-disparar-opinión"}, {"valor": 7, "palabra": "expresidente-calderón-enojado"}, {"valor": 7, "palabra": "calderón-enojado-porque"}, {"valor": 7, "palabra": "enojado-porque-esposa"}, {"valor": 7, "palabra": "porque-esposa-moreno"}, {"valor": 7, "palabra": "esposa-moreno-cortés"}, {"valor": 7, "palabra": "moreno-cortés-apoderarse"}, {"valor": 7, "palabra": "cortés-apoderarse-priancho"}, {"valor": 7, "palabra": "apoderarse-priancho-opinión"}, {"valor": 7, "palabra": "cuñado-ricardo-monreal"}, {"valor": 6, "palabra": "asesora-seguridad-blanca"}, {"valor": 6, "palabra": "juicio-político-contra"}, {"valor": 6, "palabra": "director-desarrollo-social"}, {"valor": 5, "palabra": "sebastián-piñera-expresidente"}, {"valor": 5, "palabra": "político-contra-ministro"}, {"valor": 4, "palabra": "seguridad-blanca-elizabeth"}, {"valor": 4, "palabra": "blanca-elizabeth-sherwoodrandall"}, {"valor": 4, "palabra": "investigación-asunto-cerrado"}, {"valor": 4, "palabra": "méxico-estados-unidos"}, {"valor": 4, "palabra": "paquete-reformas-presidente"}], "MEX - Medios CDMX 2 - TW": [{"valor": 10, "palabra": "juicio-político-contra"}, {"valor": 10, "palabra": "director-desarrollo-social"}, {"valor": 7, "palabra": "presidente-andrés-manuel"}, {"valor": 6, "palabra": "expresidente-sebastián-piñera"}, {"valor": 6, "palabra": "político-contra-ministro"}, {"valor": 6, "palabra": "desarrollo-social-fresnillo"}, {"valor": 5, "palabra": "merecemos-juzgadores-podremos"}, {"valor": 5, "palabra": "juzgadores-podremos-elegir"}, {"valor": 5, "palabra": "infonavit-puedes-comprarla"}, {"valor": 5, "palabra": "social-fresnillo-zacatecas"}, {"valor": 5, "palabra": "andrés-manuel-obrador"}, {"valor": 4, "palabra": "podremos-elegir-discuten"}, {"valor": 4, "palabra": "elegir-discuten-propuesta"}, {"valor": 4, "palabra": "estado-casarrentero-rentas"}, {"valor": 4, "palabra": "casarrentero-rentas-infonavit"}, {"valor": 4, "palabra": "rentas-infonavit-puedes"}, {"valor": 4, "palabra": "puedes-comprarla-iniciativa"}, {"valor": 4, "palabra": "tragos-naranja-videos"}, {"valor": 4, "palabra": "naranja-videos-fiesta"}, {"valor": 4, "palabra": "videos-fiesta-samuel"}, {"valor": 4, "palabra": "fiesta-samuel-amigos"}, {"valor": 4, "palabra": "samuel-amigos-álvarez"}, {"valor": 4, "palabra": "amigos-álvarez-máynez"}, {"valor": 4, "palabra": "álvarez-máynez-cuestiona"}, {"valor": 4, "palabra": "colosio-barrales-palazuelos"}, {"valor": 4, "palabra": "violencia-política-género"}, {"valor": 3, "palabra": "judicial-merecemos-juzgadores"}, {"valor": 3, "palabra": "anuncia-jornada-registro"}, {"valor": 3, "palabra": "jornada-registro-consulados"}, {"valor": 3, "palabra": "registro-consulados-canadá"}]}, "2024-02-08-2024-02-08": {"MEX - Influenciadores de Interés 2 - TW": [{"valor": 3, "palabra": "primera-estuve-frente"}, {"valor": 3, "palabra": "estuve-frente-personas"}, {"valor": 3, "palabra": "atentado-contra-habría"}, {"valor": 3, "palabra": "contra-habría-disparado"}, {"valor": 3, "palabra": "andrés-manuel-obrador"}, {"valor": 2, "palabra": "chapala-grande-capacidad"}, {"valor": 2, "palabra": "grande-capacidad-debido"}, {"valor": 2, "palabra": "capacidad-debido-intensa"}, {"valor": 2, "palabra": "debido-intensa-sequía"}, {"valor": 2, "palabra": "intensa-sequía-algunas"}, {"valor": 2, "palabra": "sequía-algunas-lanchas"}, {"valor": 2, "palabra": "algunas-lanchas-pueden"}, {"valor": 2, "palabra": "lanchas-pueden-avanzar"}, {"valor": 2, "palabra": "reformas-presidente-homenaje"}, {"valor": 2, "palabra": "presidente-homenaje-fracaso"}, {"valor": 2, "palabra": "homenaje-fracaso-gobierno"}, {"valor": 2, "palabra": "fracaso-gobierno-diputado"}, {"valor": 2, "palabra": "gobierno-diputado-triana"}, {"valor": 2, "palabra": "diputado-triana-durante"}, {"valor": 2, "palabra": "triana-durante-inicio"}, {"valor": 2, "palabra": "durante-inicio-debate"}, {"valor": 2, "palabra": "inicio-debate-paquete"}, {"valor": 2, "palabra": "debate-paquete-presidencial"}, {"valor": 2, "palabra": "paquete-presidencial-discusión"}, {"valor": 2, "palabra": "frente-personas-acuerdo"}, {"valor": 2, "palabra": "personas-acuerdo-autoridades"}, {"valor": 2, "palabra": "acuerdo-autoridades-planificaron"}, {"valor": 2, "palabra": "autoridades-planificaron-materializaron"}, {"valor": 2, "palabra": "planificaron-materializaron-atentado"}, {"valor": 2, "palabra": "materializaron-atentado-contra"}], "MEX - Influenciadores de Interés - TW": [{"valor": 2, "palabra": "apoyan-revisar-funcionamiento"}, {"valor": 2, "palabra": "revisar-funcionamiento-semáforo"}, {"valor": 1, "palabra": "rafael-cardona-división"}, {"valor": 1, "palabra": "cardona-división-propósito"}, {"valor": 1, "palabra": "división-propósito-logrado"}, {"valor": 1, "palabra": "propósito-logrado-acompañarte"}, {"valor": 1, "palabra": "logrado-acompañarte-amigos"}, {"valor": 1, "palabra": "acompañarte-amigos-pejistas"}, {"valor": 1, "palabra": "amigos-pejistas-permítanme"}, {"valor": 1, "palabra": "pejistas-permítanme-ministra"}, {"valor": 1, "palabra": "permítanme-ministra-pueblo"}, {"valor": 1, "palabra": "ministra-pueblo-traidores"}, {"valor": 1, "palabra": "pueblo-traidores-patria"}, {"valor": 1, "palabra": "traidores-patria-reputísima"}, {"valor": 1, "palabra": "patria-reputísima-atención"}, {"valor": 1, "palabra": "reputísima-atención-gracias"}, {"valor": 1, "palabra": "atención-gracias-cinismo"}, {"valor": 1, "palabra": "gracias-cinismo-desvergüenza"}, {"valor": 1, "palabra": "cinismo-desvergüenza-resulta"}, {"valor": 1, "palabra": "desvergüenza-resulta-huerta"}, {"valor": 1, "palabra": "resulta-huerta-diputado"}, {"valor": 1, "palabra": "huerta-diputado-morena"}, {"valor": 1, "palabra": "diputado-morena-hábiles"}, {"valor": 1, "palabra": "morena-hábiles-pederastia"}, {"valor": 1, "palabra": "hábiles-pederastia-practicaba"}, {"valor": 1, "palabra": "pederastia-practicaba-asunto"}, {"valor": 1, "palabra": "practicaba-asunto-privado"}, {"valor": 1, "palabra": "asunto-privado-creerse"}, {"valor": 1, "palabra": "privado-creerse-ataque"}, {"valor": 1, "palabra": "creerse-ataque-estados"}], "MEX - Medios CDMX - TW": [{"valor": 12, "palabra": "cantante-corridos-tumbados"}, {"valor": 8, "palabra": "hermano-alcalde-sombrerete"}, {"valor": 7, "palabra": "cecilio-murillo-hermano"}, {"valor": 7, "palabra": "montana-cantante-corridos"}, {"valor": 6, "palabra": "murillo-hermano-alcalde"}, {"valor": 5, "palabra": "desarrollo-social-fresnillo"}, {"valor": 5, "palabra": "islandia-tercera-diciembre"}, {"valor": 4, "palabra": "cuñado-ricardo-monreal"}, {"valor": 4, "palabra": "presidente-andrés-manuel"}, {"valor": 4, "palabra": "carretera-tijuanaplayas-rosarito"}, {"valor": 4, "palabra": "corridos-tumbados-asesinado"}, {"valor": 3, "palabra": "consecutivos-temperaturas-cálidas"}, {"valor": 3, "palabra": "temperaturas-cálidas-preindustrial"}, {"valor": 3, "palabra": "intentar-extorsionar-gobierno"}, {"valor": 3, "palabra": "ricardo-monreal-asesinado"}, {"valor": 3, "palabra": "monreal-asesinado-balazos"}, {"valor": 3, "palabra": "asesinan-hermano-alcalde"}, {"valor": 3, "palabra": "alcalde-sombrerete-zacatecas"}, {"valor": 3, "palabra": "asesinan-cecilio-murillo"}, {"valor": 3, "palabra": "investido-caballero-nacional"}, {"valor": 3, "palabra": "caballero-nacional-legión"}, {"valor": 3, "palabra": "nacional-legión-francia"}, {"valor": 3, "palabra": "cárcel-exdiputado-morena"}, {"valor": 3, "palabra": "exdiputado-morena-sexual"}, {"valor": 3, "palabra": "asesinan-montana-cantante"}, {"valor": 3, "palabra": "erupción-volcán-islandia"}, {"valor": 3, "palabra": "volcán-islandia-tercera"}, {"valor": 3, "palabra": "empresas-fuerzas-armadas"}, {"valor": 3, "palabra": "secretario-desarrollo-social"}, {"valor": 3, "palabra": "social-fresnillo-zacatecas"}], "MEX - Medios CDMX 2 - TW": [{"valor": 5, "palabra": "fábrica-descrédito-espontáneo"}, {"valor": 5, "palabra": "descrédito-espontáneo-ataques"}, {"valor": 5, "palabra": "espontáneo-ataques-vendrán"}, {"valor": 5, "palabra": "ataques-vendrán-porque"}, {"valor": 5, "palabra": "vendrán-porque-dinero"}, {"valor": 5, "palabra": "estados-unidos-méxico"}, {"valor": 5, "palabra": "director-desarrollo-social"}, {"valor": 4, "palabra": "recursos-tribunal-electoral"}, {"valor": 4, "palabra": "tribunal-electoral-revoca"}, {"valor": 4, "palabra": "electoral-revoca-contra"}, {"valor": 4, "palabra": "revoca-contra-denisse"}, {"valor": 4, "palabra": "contra-denisse-dresser"}, {"valor": 4, "palabra": "denisse-dresser-denuncia"}, {"valor": 4, "palabra": "dresser-denuncia-andrea"}, {"valor": 4, "palabra": "denuncia-andrea-chávez"}, {"valor": 4, "palabra": "cantante-corridos-tumbados"}, {"valor": 3, "palabra": "proyecto-derogar-aborto"}, {"valor": 3, "palabra": "violencia-política-género"}, {"valor": 3, "palabra": "tenemos-diferencias-entrevista"}, {"valor": 3, "palabra": "diferencias-entrevista-hablado"}, {"valor": 3, "palabra": "entrevista-hablado-claudio"}, {"valor": 3, "palabra": "hablado-claudio-trinchera"}, {"valor": 3, "palabra": "alcalde-ciudad-victoria"}, {"valor": 3, "palabra": "desarrollo-social-fresnillo"}, {"valor": 3, "palabra": "andanzas-samuelmáynez-causan"}, {"valor": 3, "palabra": "samuelmáynez-causan-críticas"}, {"valor": 3, "palabra": "causan-críticas-cuando"}, {"valor": 3, "palabra": "críticas-cuando-campaña"}, {"valor": 3, "palabra": "monarca-riesgo-número"}, {"valor": 3, "palabra": "riesgo-número-mariposas"}]}}