{"2024-02-12-2024-02-12": {"MEX - Influenciadores de Interés - TW": [{"valor": 13, "palabra": "presidente"}, {"valor": 11, "palabra": "abrazo"}, {"valor": 9, "palabra": "méxico"}, {"valor": 8, "palabra": "nuestra"}, {"valor": 7, "palabra": "gobierno"}, {"valor": 7, "palabra": "sheinbaum"}, {"valor": 7, "palabra": "nacional"}, {"valor": 7, "palabra": "democracia"}, {"valor": 7, "palabra": "porque"}, {"valor": 6, "palabra": "contra"}, {"valor": 5, "palabra": "política"}, {"valor": 5, "palabra": "gracias"}, {"valor": 5, "palabra": "pueblo"}, {"valor": 5, "palabra": "obrador"}, {"valor": 5, "palabra": "febrero"}, {"valor": 5, "palabra": "violencia"}, {"valor": 5, "palabra": "elección"}, {"valor": 5, "palabra": "siempre"}, {"valor": 5, "palabra": "nuestro"}, {"valor": 5, "palabra": "xóchitl"}, {"valor": 4, "palabra": "familia"}, {"valor": 4, "palabra": "seguridad"}, {"valor": 4, "palabra": "países"}, {"valor": 4, "palabra": "claudia"}, {"valor": 4, "palabra": "social"}, {"valor": 4, "palabra": "reforma"}, {"valor": 4, "palabra": "morena"}, {"valor": 4, "palabra": "además"}, {"valor": 4, "palabra": "reformas"}, {"valor": 4, "palabra": "presidencial"}, {"valor": 4, "palabra": "candidata"}, {"valor": 4, "palabra": "mujeres"}, {"valor": 4, "palabra": "fortuna"}, {"valor": 4, "palabra": "andrés"}, {"valor": 4, "palabra": "gálvez"}, {"valor": 4, "palabra": "felipe"}, {"valor": 4, "palabra": "calderón"}, {"valor": 3, "palabra": "chiefs"}, {"valor": 3, "palabra": "triunfo"}, {"valor": 3, "palabra": "felicidades"}], "MEX - Influenciadores de Interés 2 - TW": [{"valor": 24, "palabra": "porque"}, {"valor": 20, "palabra": "presidente"}, {"valor": 18, "palabra": "cuando"}, {"valor": 17, "palabra": "méxico"}, {"valor": 17, "palabra": "gobierno"}, {"valor": 15, "palabra": "ciudad"}, {"valor": 12, "palabra": "campaña"}, {"valor": 11, "palabra": "gracias"}, {"valor": 10, "palabra": "zócalo"}, {"valor": 10, "palabra": "mujeres"}, {"valor": 10, "palabra": "contra"}, {"valor": 9, "palabra": "morena"}, {"valor": 9, "palabra": "obrador"}, {"valor": 8, "palabra": "personas"}, {"valor": 7, "palabra": "seguridad"}, {"valor": 7, "palabra": "política"}, {"valor": 7, "palabra": "trabajo"}, {"valor": 7, "palabra": "estaba"}, {"valor": 6, "palabra": "también"}, {"valor": 6, "palabra": "xóchitl"}, {"valor": 6, "palabra": "mañanera"}, {"valor": 6, "palabra": "electoral"}, {"valor": 6, "palabra": "investigación"}, {"valor": 6, "palabra": "atención"}, {"valor": 6, "palabra": "dinero"}, {"valor": 6, "palabra": "entonces"}, {"valor": 5, "palabra": "estamos"}, {"valor": 5, "palabra": "manera"}, {"valor": 5, "palabra": "andrés"}, {"valor": 5, "palabra": "manuel"}, {"valor": 5, "palabra": "familiares"}, {"valor": 5, "palabra": "garcía"}, {"valor": 5, "palabra": "calderón"}, {"valor": 5, "palabra": "haciendo"}, {"valor": 5, "palabra": "gobernación"}, {"valor": 5, "palabra": "infección"}, {"valor": 5, "palabra": "candidata"}, {"valor": 5, "palabra": "feminista"}, {"valor": 5, "palabra": "ustedes"}, {"valor": 5, "palabra": "servicio"}], "MEX - Medios CDMX - TW": [{"valor": 89, "palabra": "méxico"}, {"valor": 62, "palabra": "presidente"}, {"valor": 52, "palabra": "febrero"}, {"valor": 48, "palabra": "personas"}, {"valor": 46, "palabra": "contra"}, {"valor": 40, "palabra": "carlos"}, {"valor": 36, "palabra": "durante"}, {"valor": 35, "palabra": "opinión"}, {"valor": 35, "palabra": "escribe"}, {"valor": 34, "palabra": "seguridad"}, {"valor": 34, "palabra": "tiempo"}, {"valor": 32, "palabra": "reforma"}, {"valor": 32, "palabra": "kansas"}, {"valor": 32, "palabra": "taylor"}, {"valor": 32, "palabra": "estados"}, {"valor": 31, "palabra": "gobierno"}, {"valor": 30, "palabra": "historia"}, {"valor": 29, "palabra": "francisco"}, {"valor": 29, "palabra": "millones"}, {"valor": 29, "palabra": "elecciones"}, {"valor": 28, "palabra": "unidos"}, {"valor": 26, "palabra": "chiefs"}, {"valor": 25, "palabra": "violencia"}, {"valor": 24, "palabra": "estado"}, {"valor": 24, "palabra": "reformas"}, {"valor": 23, "palabra": "fueron"}, {"valor": 23, "palabra": "detalles"}, {"valor": 22, "palabra": "mahomes"}, {"valor": 22, "palabra": "primer"}, {"valor": 22, "palabra": "ciudad"}, {"valor": 21, "palabra": "autoridades"}, {"valor": 21, "palabra": "semana"}, {"valor": 20, "palabra": "presidencial"}, {"valor": 20, "palabra": "sexenio"}, {"valor": 20, "palabra": "también"}, {"valor": 20, "palabra": "nuestra"}, {"valor": 20, "palabra": "campaña"}, {"valor": 19, "palabra": "podría"}, {"valor": 19, "palabra": "debido"}, {"valor": 18, "palabra": "travis"}], "MEX - Medios CDMX 2 - TW": [{"valor": 61, "palabra": "méxico"}, {"valor": 55, "palabra": "presidente"}, {"valor": 30, "palabra": "morena"}, {"valor": 28, "palabra": "tiempo"}, {"valor": 27, "palabra": "febrero"}, {"valor": 25, "palabra": "contra"}, {"valor": 24, "palabra": "gobierno"}, {"valor": 22, "palabra": "personas"}, {"valor": 21, "palabra": "campaña"}, {"valor": 21, "palabra": "presidencial"}, {"valor": 21, "palabra": "calderón"}, {"valor": 21, "palabra": "completa"}, {"valor": 20, "palabra": "reforma"}, {"valor": 19, "palabra": "xóchitl"}, {"valor": 18, "palabra": "candidata"}, {"valor": 17, "palabra": "ciudad"}, {"valor": 16, "palabra": "también"}, {"valor": 16, "palabra": "autoridades"}, {"valor": 16, "palabra": "chiefs"}, {"valor": 16, "palabra": "cuando"}, {"valor": 16, "palabra": "gracias"}, {"valor": 16, "palabra": "judicial"}, {"valor": 15, "palabra": "ataque"}, {"valor": 15, "palabra": "durante"}, {"valor": 15, "palabra": "obrador"}, {"valor": 15, "palabra": "carlos"}, {"valor": 14, "palabra": "sociales"}, {"valor": 14, "palabra": "política"}, {"valor": 14, "palabra": "primer"}, {"valor": 14, "palabra": "seguridad"}, {"valor": 14, "palabra": "opinión"}, {"valor": 13, "palabra": "familia"}, {"valor": 13, "palabra": "gálvez"}, {"valor": 13, "palabra": "sheinbaum"}, {"valor": 13, "palabra": "semana"}, {"valor": 12, "palabra": "elecciones"}, {"valor": 12, "palabra": "mahomes"}, {"valor": 12, "palabra": "kansas"}, {"valor": 12, "palabra": "cuatro"}, {"valor": 12, "palabra": "guerra"}]}, "2024-02-13-2024-02-13": {"MEX - Influenciadores de Interés - TW": [{"valor": 16, "palabra": "presidente"}, {"valor": 14, "palabra": "gracias"}, {"valor": 12, "palabra": "elección"}, {"valor": 11, "palabra": "democracia"}, {"valor": 9, "palabra": "porque"}, {"valor": 8, "palabra": "méxico"}, {"valor": 8, "palabra": "nuestra"}, {"valor": 8, "palabra": "carlos"}, {"valor": 7, "palabra": "contra"}, {"valor": 7, "palabra": "siempre"}, {"valor": 7, "palabra": "cartón"}, {"valor": 7, "palabra": "abrazo"}, {"valor": 6, "palabra": "felipe"}, {"valor": 6, "palabra": "entrevista"}, {"valor": 6, "palabra": "personas"}, {"valor": 6, "palabra": "gobierno"}, {"valor": 6, "palabra": "completa"}, {"valor": 6, "palabra": "crimen"}, {"valor": 6, "palabra": "martes"}, {"valor": 5, "palabra": "morena"}, {"valor": 5, "palabra": "también"}, {"valor": 5, "palabra": "atiendo"}, {"valor": 5, "palabra": "xóchitl"}, {"valor": 5, "palabra": "electoral"}, {"valor": 5, "palabra": "organizado"}, {"valor": 5, "palabra": "febrero"}, {"valor": 5, "palabra": "estamos"}, {"valor": 5, "palabra": "estado"}, {"valor": 5, "palabra": "pendiente"}, {"valor": 4, "palabra": "muchas"}, {"valor": 4, "palabra": "político"}, {"valor": 4, "palabra": "reforma"}, {"valor": 4, "palabra": "justicia"}, {"valor": 4, "palabra": "gálvez"}, {"valor": 4, "palabra": "calderón"}, {"valor": 4, "palabra": "cárdenas"}, {"valor": 4, "palabra": "familia"}, {"valor": 4, "palabra": "haciendo"}, {"valor": 4, "palabra": "pueblo"}, {"valor": 4, "palabra": "marcha"}], "MEX - Influenciadores de Interés 2 - TW": [{"valor": 30, "palabra": "méxico"}, {"valor": 23, "palabra": "gobierno"}, {"valor": 15, "palabra": "seguridad"}, {"valor": 15, "palabra": "presidente"}, {"valor": 13, "palabra": "contra"}, {"valor": 12, "palabra": "también"}, {"valor": 12, "palabra": "porque"}, {"valor": 10, "palabra": "personas"}, {"valor": 10, "palabra": "andrés"}, {"valor": 9, "palabra": "sistema"}, {"valor": 9, "palabra": "gracias"}, {"valor": 9, "palabra": "pueblo"}, {"valor": 9, "palabra": "corrupción"}, {"valor": 8, "palabra": "invertir"}, {"valor": 8, "palabra": "dinero"}, {"valor": 8, "palabra": "empresa"}, {"valor": 8, "palabra": "cuando"}, {"valor": 8, "palabra": "febrero"}, {"valor": 8, "palabra": "justicia"}, {"valor": 8, "palabra": "carlos"}, {"valor": 8, "palabra": "estado"}, {"valor": 7, "palabra": "crecimiento"}, {"valor": 7, "palabra": "inversiones"}, {"valor": 7, "palabra": "además"}, {"valor": 7, "palabra": "semana"}, {"valor": 7, "palabra": "estamos"}, {"valor": 7, "palabra": "ciudad"}, {"valor": 7, "palabra": "nuestro"}, {"valor": 6, "palabra": "después"}, {"valor": 6, "palabra": "pueden"}, {"valor": 6, "palabra": "quiere"}, {"valor": 6, "palabra": "estrategia"}, {"valor": 6, "palabra": "empresario"}, {"valor": 6, "palabra": "consejo"}, {"valor": 6, "palabra": "morena"}, {"valor": 6, "palabra": "siempre"}, {"valor": 6, "palabra": "buenos"}, {"valor": 6, "palabra": "desarrollo"}, {"valor": 6, "palabra": "empresas"}, {"valor": 5, "palabra": "cualquier"}], "MEX - Medios CDMX - TW": [{"valor": 138, "palabra": "méxico"}, {"valor": 86, "palabra": "febrero"}, {"valor": 74, "palabra": "contra"}, {"valor": 71, "palabra": "presidente"}, {"valor": 58, "palabra": "historia"}, {"valor": 52, "palabra": "personas"}, {"valor": 49, "palabra": "carlos"}, {"valor": 44, "palabra": "escribe"}, {"valor": 43, "palabra": "gobierno"}, {"valor": 43, "palabra": "nacional"}, {"valor": 38, "palabra": "seguridad"}, {"valor": 38, "palabra": "estado"}, {"valor": 37, "palabra": "opinión"}, {"valor": 35, "palabra": "martes"}, {"valor": 34, "palabra": "información"}, {"valor": 32, "palabra": "detalles"}, {"valor": 32, "palabra": "durante"}, {"valor": 32, "palabra": "mexicano"}, {"valor": 31, "palabra": "estados"}, {"valor": 31, "palabra": "millones"}, {"valor": 29, "palabra": "fueron"}, {"valor": 29, "palabra": "alcaldía"}, {"valor": 28, "palabra": "morena"}, {"valor": 27, "palabra": "candidata"}, {"valor": 25, "palabra": "transporte"}, {"valor": 24, "palabra": "autoridades"}, {"valor": 24, "palabra": "reforma"}, {"valor": 23, "palabra": "violencia"}, {"valor": 23, "palabra": "pasado"}, {"valor": 23, "palabra": "cuando"}, {"valor": 23, "palabra": "unidos"}, {"valor": 22, "palabra": "proceso"}, {"valor": 21, "palabra": "conoce"}, {"valor": 21, "palabra": "chofer"}, {"valor": 21, "palabra": "público"}, {"valor": 21, "palabra": "después"}, {"valor": 21, "palabra": "obrador"}, {"valor": 21, "palabra": "primera"}, {"valor": 21, "palabra": "relación"}, {"valor": 20, "palabra": "reformas"}], "MEX - Medios CDMX 2 - TW": [{"valor": 66, "palabra": "presidente"}, {"valor": 60, "palabra": "méxico"}, {"valor": 57, "palabra": "contra"}, {"valor": 38, "palabra": "morena"}, {"valor": 37, "palabra": "carlos"}, {"valor": 35, "palabra": "febrero"}, {"valor": 32, "palabra": "gobierno"}, {"valor": 26, "palabra": "candidata"}, {"valor": 26, "palabra": "presidencial"}, {"valor": 25, "palabra": "estados"}, {"valor": 22, "palabra": "personas"}, {"valor": 22, "palabra": "obrador"}, {"valor": 22, "palabra": "unidos"}, {"valor": 20, "palabra": "mexicano"}, {"valor": 20, "palabra": "millones"}, {"valor": 19, "palabra": "elecciones"}, {"valor": 19, "palabra": "violencia"}, {"valor": 19, "palabra": "reforma"}, {"valor": 19, "palabra": "nacional"}, {"valor": 18, "palabra": "sheinbaum"}, {"valor": 17, "palabra": "autoridades"}, {"valor": 17, "palabra": "opinión"}, {"valor": 16, "palabra": "próximo"}, {"valor": 16, "palabra": "martes"}, {"valor": 15, "palabra": "iniciativa"}, {"valor": 14, "palabra": "judicial"}, {"valor": 14, "palabra": "cuando"}, {"valor": 14, "palabra": "campaña"}, {"valor": 14, "palabra": "pueblo"}, {"valor": 14, "palabra": "mexicanos"}, {"valor": 14, "palabra": "estado"}, {"valor": 13, "palabra": "tiroteo"}, {"valor": 13, "palabra": "completa"}, {"valor": 12, "palabra": "andrés"}, {"valor": 12, "palabra": "afirmó"}, {"valor": 12, "palabra": "partido"}, {"valor": 12, "palabra": "información"}, {"valor": 12, "palabra": "elección"}, {"valor": 12, "palabra": "reformas"}, {"valor": 11, "palabra": "público"}]}, "2024-02-14-2024-02-14": {"MEX - Influenciadores de Interés - TW": [{"valor": 12, "palabra": "méxico"}, {"valor": 9, "palabra": "abrazo"}, {"valor": 8, "palabra": "presidente"}, {"valor": 8, "palabra": "porque"}, {"valor": 7, "palabra": "democracia"}, {"valor": 7, "palabra": "entrevista"}, {"valor": 7, "palabra": "nuestra"}, {"valor": 7, "palabra": "pendiente"}, {"valor": 6, "palabra": "carlos"}, {"valor": 6, "palabra": "familia"}, {"valor": 6, "palabra": "estamos"}, {"valor": 5, "palabra": "sociales"}, {"valor": 5, "palabra": "pueblo"}, {"valor": 5, "palabra": "posible"}, {"valor": 5, "palabra": "completa"}, {"valor": 5, "palabra": "atención"}, {"valor": 5, "palabra": "francisco"}, {"valor": 5, "palabra": "campaña"}, {"valor": 5, "palabra": "reporte"}, {"valor": 5, "palabra": "gobierno"}, {"valor": 4, "palabra": "xóchitl"}, {"valor": 4, "palabra": "gálvez"}, {"valor": 4, "palabra": "nuestros"}, {"valor": 4, "palabra": "cuando"}, {"valor": 4, "palabra": "vecinas"}, {"valor": 4, "palabra": "vecinos"}, {"valor": 4, "palabra": "también"}, {"valor": 4, "palabra": "estado"}, {"valor": 4, "palabra": "derecho"}, {"valor": 4, "palabra": "contra"}, {"valor": 4, "palabra": "héctor"}, {"valor": 4, "palabra": "aguilar"}, {"valor": 4, "palabra": "personas"}, {"valor": 4, "palabra": "febrero"}, {"valor": 4, "palabra": "gracias"}, {"valor": 4, "palabra": "durante"}, {"valor": 4, "palabra": "miguel"}, {"valor": 4, "palabra": "política"}, {"valor": 4, "palabra": "ubicación"}, {"valor": 4, "palabra": "realizar"}], "MEX - Influenciadores de Interés 2 - TW": [{"valor": 22, "palabra": "méxico"}, {"valor": 20, "palabra": "presidente"}, {"valor": 19, "palabra": "porque"}, {"valor": 12, "palabra": "xóchitl"}, {"valor": 11, "palabra": "también"}, {"valor": 11, "palabra": "obrador"}, {"valor": 10, "palabra": "gobierno"}, {"valor": 10, "palabra": "morena"}, {"valor": 9, "palabra": "dinero"}, {"valor": 9, "palabra": "contra"}, {"valor": 8, "palabra": "febrero"}, {"valor": 8, "palabra": "ciudad"}, {"valor": 8, "palabra": "nacional"}, {"valor": 8, "palabra": "millones"}, {"valor": 7, "palabra": "seguridad"}, {"valor": 7, "palabra": "cuando"}, {"valor": 7, "palabra": "gálvez"}, {"valor": 7, "palabra": "candidata"}, {"valor": 6, "palabra": "parece"}, {"valor": 6, "palabra": "personas"}, {"valor": 6, "palabra": "andrés"}, {"valor": 6, "palabra": "trabajo"}, {"valor": 6, "palabra": "siempre"}, {"valor": 6, "palabra": "cualquier"}, {"valor": 6, "palabra": "además"}, {"valor": 6, "palabra": "estado"}, {"valor": 5, "palabra": "estamos"}, {"valor": 5, "palabra": "autoridades"}, {"valor": 5, "palabra": "oposición"}, {"valor": 5, "palabra": "momento"}, {"valor": 5, "palabra": "acuerdo"}, {"valor": 5, "palabra": "agresiones"}, {"valor": 5, "palabra": "heridos"}, {"valor": 5, "palabra": "militar"}, {"valor": 5, "palabra": "nuestro"}, {"valor": 5, "palabra": "manuel"}, {"valor": 5, "palabra": "mañana"}, {"valor": 5, "palabra": "saludos"}, {"valor": 5, "palabra": "francisco"}, {"valor": 4, "palabra": "aunque"}], "MEX - Medios CDMX - TW": [{"valor": 120, "palabra": "méxico"}, {"valor": 91, "palabra": "febrero"}, {"valor": 72, "palabra": "presidente"}, {"valor": 70, "palabra": "contra"}, {"valor": 63, "palabra": "detalles"}, {"valor": 49, "palabra": "gobierno"}, {"valor": 48, "palabra": "tiroteo"}, {"valor": 48, "palabra": "miércoles"}, {"valor": 47, "palabra": "durante"}, {"valor": 47, "palabra": "personas"}, {"valor": 47, "palabra": "nacional"}, {"valor": 46, "palabra": "seguridad"}, {"valor": 40, "palabra": "valentín"}, {"valor": 38, "palabra": "opinión"}, {"valor": 38, "palabra": "desfile"}, {"valor": 37, "palabra": "violencia"}, {"valor": 37, "palabra": "cuando"}, {"valor": 33, "palabra": "escribe"}, {"valor": 33, "palabra": "kansas"}, {"valor": 32, "palabra": "estado"}, {"valor": 30, "palabra": "ciudad"}, {"valor": 30, "palabra": "fueron"}, {"valor": 30, "palabra": "pareja"}, {"valor": 29, "palabra": "crisis"}, {"valor": 29, "palabra": "información"}, {"valor": 29, "palabra": "microsismos"}, {"valor": 28, "palabra": "reforma"}, {"valor": 28, "palabra": "amistad"}, {"valor": 28, "palabra": "momento"}, {"valor": 27, "palabra": "persona"}, {"valor": 26, "palabra": "morena"}, {"valor": 25, "palabra": "chiefs"}, {"valor": 25, "palabra": "fiscal"}, {"valor": 25, "palabra": "millones"}, {"valor": 25, "palabra": "autoridades"}, {"valor": 24, "palabra": "mexicano"}, {"valor": 24, "palabra": "estados"}, {"valor": 24, "palabra": "reformas"}, {"valor": 24, "palabra": "alcaldía"}, {"valor": 23, "palabra": "carlos"}], "MEX - Medios CDMX 2 - TW": [{"valor": 72, "palabra": "méxico"}, {"valor": 52, "palabra": "presidente"}, {"valor": 37, "palabra": "xóchitl"}, {"valor": 37, "palabra": "contra"}, {"valor": 36, "palabra": "febrero"}, {"valor": 31, "palabra": "tiroteo"}, {"valor": 27, "palabra": "valentín"}, {"valor": 27, "palabra": "estados"}, {"valor": 27, "palabra": "morena"}, {"valor": 25, "palabra": "gálvez"}, {"valor": 23, "palabra": "ciudad"}, {"valor": 22, "palabra": "durante"}, {"valor": 21, "palabra": "estado"}, {"valor": 21, "palabra": "seguridad"}, {"valor": 21, "palabra": "españa"}, {"valor": 21, "palabra": "miércoles"}, {"valor": 21, "palabra": "kansas"}, {"valor": 20, "palabra": "policía"}, {"valor": 20, "palabra": "desfile"}, {"valor": 19, "palabra": "sheinbaum"}, {"valor": 19, "palabra": "unidos"}, {"valor": 19, "palabra": "millones"}, {"valor": 18, "palabra": "gobierno"}, {"valor": 18, "palabra": "obrador"}, {"valor": 17, "palabra": "también"}, {"valor": 17, "palabra": "electoral"}, {"valor": 17, "palabra": "chiefs"}, {"valor": 16, "palabra": "muerto"}, {"valor": 16, "palabra": "personas"}, {"valor": 16, "palabra": "información"}, {"valor": 16, "palabra": "heridos"}, {"valor": 15, "palabra": "campaña"}, {"valor": 15, "palabra": "violencia"}, {"valor": 15, "palabra": "nacional"}, {"valor": 15, "palabra": "aseguró"}, {"valor": 15, "palabra": "política"}, {"valor": 15, "palabra": "opinión"}, {"valor": 14, "palabra": "senado"}, {"valor": 14, "palabra": "gobernador"}, {"valor": 14, "palabra": "congreso"}]}, "2024-02-15-2024-02-15": {"MEX - Influenciadores de Interés - TW": [{"valor": 16, "palabra": "gobierno"}, {"valor": 15, "palabra": "democracia"}, {"valor": 12, "palabra": "méxico"}, {"valor": 10, "palabra": "cuando"}, {"valor": 10, "palabra": "porque"}, {"valor": 10, "palabra": "quieren"}, {"valor": 9, "palabra": "presidente"}, {"valor": 8, "palabra": "domingo"}, {"valor": 7, "palabra": "morena"}, {"valor": 7, "palabra": "también"}, {"valor": 7, "palabra": "reconocer"}, {"valor": 6, "palabra": "entrevista"}, {"valor": 6, "palabra": "completa"}, {"valor": 6, "palabra": "jueves"}, {"valor": 6, "palabra": "pendiente"}, {"valor": 5, "palabra": "nacional"}, {"valor": 5, "palabra": "verdad"}, {"valor": 5, "palabra": "carlos"}, {"valor": 5, "palabra": "dinero"}, {"valor": 5, "palabra": "derechos"}, {"valor": 5, "palabra": "gracias"}, {"valor": 5, "palabra": "sheinbaum"}, {"valor": 5, "palabra": "transportistas"}, {"valor": 5, "palabra": "defender"}, {"valor": 5, "palabra": "nuestras"}, {"valor": 5, "palabra": "zócalo"}, {"valor": 5, "palabra": "estamos"}, {"valor": 4, "palabra": "registro"}, {"valor": 4, "palabra": "política"}, {"valor": 4, "palabra": "grandes"}, {"valor": 4, "palabra": "xóchitl"}, {"valor": 4, "palabra": "información"}, {"valor": 4, "palabra": "familia"}, {"valor": 4, "palabra": "actividades"}, {"valor": 4, "palabra": "claudia"}, {"valor": 4, "palabra": "estado"}, {"valor": 4, "palabra": "división"}, {"valor": 4, "palabra": "poderes"}, {"valor": 4, "palabra": "cambio"}, {"valor": 4, "palabra": "ciudadanos"}], "MEX - Influenciadores de Interés 2 - TW": [{"valor": 26, "palabra": "méxico"}, {"valor": 22, "palabra": "porque"}, {"valor": 20, "palabra": "gobierno"}, {"valor": 18, "palabra": "presidente"}, {"valor": 10, "palabra": "personas"}, {"valor": 10, "palabra": "francisco"}, {"valor": 9, "palabra": "nacional"}, {"valor": 9, "palabra": "obrador"}, {"valor": 9, "palabra": "ciudad"}, {"valor": 8, "palabra": "seguridad"}, {"valor": 8, "palabra": "reunión"}, {"valor": 7, "palabra": "vaticano"}, {"valor": 7, "palabra": "también"}, {"valor": 7, "palabra": "acuerdo"}, {"valor": 7, "palabra": "criminales"}, {"valor": 7, "palabra": "sabemos"}, {"valor": 6, "palabra": "realidad"}, {"valor": 6, "palabra": "primera"}, {"valor": 6, "palabra": "estado"}, {"valor": 6, "palabra": "roberto"}, {"valor": 6, "palabra": "sheinbaum"}, {"valor": 6, "palabra": "historia"}, {"valor": 6, "palabra": "cuando"}, {"valor": 6, "palabra": "claudia"}, {"valor": 6, "palabra": "audiencia"}, {"valor": 6, "palabra": "andrés"}, {"valor": 6, "palabra": "morena"}, {"valor": 6, "palabra": "mientras"}, {"valor": 6, "palabra": "transportistas"}, {"valor": 6, "palabra": "comparto"}, {"valor": 5, "palabra": "dinero"}, {"valor": 5, "palabra": "coalición"}, {"valor": 5, "palabra": "después"}, {"valor": 5, "palabra": "contra"}, {"valor": 5, "palabra": "cuenta"}, {"valor": 5, "palabra": "semanas"}, {"valor": 5, "palabra": "fueron"}, {"valor": 5, "palabra": "gracias"}, {"valor": 5, "palabra": "obispos"}, {"valor": 5, "palabra": "grandes"}], "MEX - Medios CDMX - TW": [{"valor": 128, "palabra": "méxico"}, {"valor": 105, "palabra": "transportistas"}, {"valor": 96, "palabra": "nacional"}, {"valor": 73, "palabra": "contra"}, {"valor": 64, "palabra": "presidente"}, {"valor": 64, "palabra": "febrero"}, {"valor": 63, "palabra": "gobierno"}, {"valor": 54, "palabra": "detalles"}, {"valor": 53, "palabra": "seguridad"}, {"valor": 51, "palabra": "durante"}, {"valor": 47, "palabra": "carreteras"}, {"valor": 45, "palabra": "personas"}, {"valor": 41, "palabra": "jueves"}, {"valor": 41, "palabra": "estado"}, {"valor": 40, "palabra": "tiroteo"}, {"valor": 38, "palabra": "montenegro"}, {"valor": 38, "palabra": "guerrero"}, {"valor": 38, "palabra": "escribe"}, {"valor": 37, "palabra": "kansas"}, {"valor": 37, "palabra": "historia"}, {"valor": 36, "palabra": "violencia"}, {"valor": 34, "palabra": "francisco"}, {"valor": 33, "palabra": "mexicano"}, {"valor": 33, "palabra": "información"}, {"valor": 33, "palabra": "opinión"}, {"valor": 32, "palabra": "morena"}, {"valor": 31, "palabra": "actriz"}, {"valor": 29, "palabra": "cuando"}, {"valor": 28, "palabra": "millones"}, {"valor": 27, "palabra": "desfile"}, {"valor": 27, "palabra": "mujeres"}, {"valor": 27, "palabra": "estados"}, {"valor": 27, "palabra": "huelga"}, {"valor": 26, "palabra": "autopista"}, {"valor": 26, "palabra": "xóchitl"}, {"valor": 26, "palabra": "candidata"}, {"valor": 26, "palabra": "piedad"}, {"valor": 25, "palabra": "también"}, {"valor": 25, "palabra": "acuerdo"}, {"valor": 25, "palabra": "crimen"}], "MEX - Medios CDMX 2 - TW": [{"valor": 89, "palabra": "méxico"}, {"valor": 55, "palabra": "morena"}, {"valor": 54, "palabra": "presidente"}, {"valor": 41, "palabra": "xóchitl"}, {"valor": 36, "palabra": "gobierno"}, {"valor": 35, "palabra": "transportistas"}, {"valor": 34, "palabra": "contra"}, {"valor": 34, "palabra": "candidata"}, {"valor": 29, "palabra": "guerrero"}, {"valor": 29, "palabra": "francisco"}, {"valor": 29, "palabra": "estados"}, {"valor": 29, "palabra": "febrero"}, {"valor": 27, "palabra": "presidencial"}, {"valor": 26, "palabra": "gálvez"}, {"valor": 26, "palabra": "ciudad"}, {"valor": 26, "palabra": "tiroteo"}, {"valor": 24, "palabra": "unidos"}, {"valor": 22, "palabra": "seguridad"}, {"valor": 22, "palabra": "nacional"}, {"valor": 20, "palabra": "obrador"}, {"valor": 20, "palabra": "kansas"}, {"valor": 19, "palabra": "durante"}, {"valor": 19, "palabra": "sheinbaum"}, {"valor": 19, "palabra": "campaña"}, {"valor": 19, "palabra": "mexicano"}, {"valor": 19, "palabra": "carreteras"}, {"valor": 18, "palabra": "guerra"}, {"valor": 18, "palabra": "estado"}, {"valor": 16, "palabra": "montenegro"}, {"valor": 16, "palabra": "primera"}, {"valor": 16, "palabra": "criminales"}, {"valor": 16, "palabra": "cuando"}, {"valor": 15, "palabra": "millones"}, {"valor": 15, "palabra": "españa"}, {"valor": 15, "palabra": "elecciones"}, {"valor": 15, "palabra": "federal"}, {"valor": 15, "palabra": "vaticano"}, {"valor": 15, "palabra": "candidato"}, {"valor": 14, "palabra": "actriz"}, {"valor": 14, "palabra": "información"}]}, "2024-02-16-2024-02-16": {"MEX - Influenciadores de Interés - TW": [{"valor": 13, "palabra": "gobierno"}, {"valor": 13, "palabra": "navalny"}, {"valor": 11, "palabra": "domingo"}, {"valor": 11, "palabra": "democracia"}, {"valor": 10, "palabra": "estado"}, {"valor": 9, "palabra": "zócalo"}, {"valor": 8, "palabra": "febrero"}, {"valor": 8, "palabra": "méxico"}, {"valor": 7, "palabra": "ciudadanos"}, {"valor": 7, "palabra": "nacional"}, {"valor": 6, "palabra": "alexei"}, {"valor": 6, "palabra": "también"}, {"valor": 6, "palabra": "porque"}, {"valor": 6, "palabra": "pendiente"}, {"valor": 6, "palabra": "electoral"}, {"valor": 6, "palabra": "contra"}, {"valor": 5, "palabra": "morena"}, {"valor": 5, "palabra": "presidente"}, {"valor": 5, "palabra": "opositor"}, {"valor": 5, "palabra": "próximo"}, {"valor": 5, "palabra": "sexenio"}, {"valor": 5, "palabra": "frente"}, {"valor": 5, "palabra": "periodistas"}, {"valor": 5, "palabra": "entrevista"}, {"valor": 4, "palabra": "trabajadores"}, {"valor": 4, "palabra": "quiere"}, {"valor": 4, "palabra": "negligencia"}, {"valor": 4, "palabra": "campaña"}, {"valor": 4, "palabra": "manifestación"}, {"valor": 4, "palabra": "candidata"}, {"valor": 4, "palabra": "viernes"}, {"valor": 4, "palabra": "defender"}, {"valor": 4, "palabra": "ciudades"}, {"valor": 4, "palabra": "marcha"}, {"valor": 4, "palabra": "muerte"}, {"valor": 4, "palabra": "régimen"}, {"valor": 4, "palabra": "violencia"}, {"valor": 4, "palabra": "abrazo"}, {"valor": 3, "palabra": "vecinos"}, {"valor": 3, "palabra": "estados"}], "MEX - Influenciadores de Interés 2 - TW": [{"valor": 18, "palabra": "porque"}, {"valor": 18, "palabra": "presidente"}, {"valor": 16, "palabra": "gracias"}, {"valor": 15, "palabra": "méxico"}, {"valor": 14, "palabra": "morena"}, {"valor": 13, "palabra": "gobierno"}, {"valor": 11, "palabra": "también"}, {"valor": 11, "palabra": "seguridad"}, {"valor": 11, "palabra": "cuando"}, {"valor": 10, "palabra": "partido"}, {"valor": 9, "palabra": "política"}, {"valor": 9, "palabra": "domingo"}, {"valor": 9, "palabra": "zócalo"}, {"valor": 8, "palabra": "trabajo"}, {"valor": 8, "palabra": "extranjero"}, {"valor": 8, "palabra": "ciudades"}, {"valor": 8, "palabra": "palacio"}, {"valor": 7, "palabra": "dinero"}, {"valor": 7, "palabra": "campaña"}, {"valor": 7, "palabra": "pública"}, {"valor": 7, "palabra": "personas"}, {"valor": 7, "palabra": "garcía"}, {"valor": 7, "palabra": "corazón"}, {"valor": 6, "palabra": "social"}, {"valor": 6, "palabra": "transportistas"}, {"valor": 6, "palabra": "carreteras"}, {"valor": 6, "palabra": "obrador"}, {"valor": 6, "palabra": "claudia"}, {"valor": 6, "palabra": "marcha"}, {"valor": 6, "palabra": "democracia"}, {"valor": 5, "palabra": "comparto"}, {"valor": 5, "palabra": "movimiento"}, {"valor": 5, "palabra": "candidata"}, {"valor": 5, "palabra": "cambio"}, {"valor": 5, "palabra": "reunión"}, {"valor": 5, "palabra": "abrazos"}, {"valor": 5, "palabra": "estados"}, {"valor": 5, "palabra": "contra"}, {"valor": 5, "palabra": "muchísimas"}, {"valor": 5, "palabra": "nuestro"}], "MEX - Medios CDMX - TW": [{"valor": 101, "palabra": "méxico"}, {"valor": 72, "palabra": "detalles"}, {"valor": 68, "palabra": "contra"}, {"valor": 65, "palabra": "presidente"}, {"valor": 64, "palabra": "gobierno"}, {"valor": 58, "palabra": "febrero"}, {"valor": 51, "palabra": "muerte"}, {"valor": 45, "palabra": "navalny"}, {"valor": 43, "palabra": "nacional"}, {"valor": 41, "palabra": "viernes"}, {"valor": 39, "palabra": "opositor"}, {"valor": 35, "palabra": "escribe"}, {"valor": 34, "palabra": "información"}, {"valor": 32, "palabra": "personas"}, {"valor": 32, "palabra": "mexicano"}, {"valor": 31, "palabra": "autoridades"}, {"valor": 31, "palabra": "dólares"}, {"valor": 30, "palabra": "seguridad"}, {"valor": 30, "palabra": "durante"}, {"valor": 29, "palabra": "estado"}, {"valor": 29, "palabra": "trabajadores"}, {"valor": 28, "palabra": "millones"}, {"valor": 28, "palabra": "prisión"}, {"valor": 27, "palabra": "nuestra"}, {"valor": 27, "palabra": "alexéi"}, {"valor": 26, "palabra": "cuando"}, {"valor": 24, "palabra": "mexicana"}, {"valor": 24, "palabra": "fueron"}, {"valor": 24, "palabra": "estados"}, {"valor": 24, "palabra": "ciudad"}, {"valor": 24, "palabra": "tiroteo"}, {"valor": 23, "palabra": "xóchitl"}, {"valor": 23, "palabra": "familia"}, {"valor": 23, "palabra": "aseguró"}, {"valor": 23, "palabra": "mexicanos"}, {"valor": 22, "palabra": "además"}, {"valor": 22, "palabra": "después"}, {"valor": 22, "palabra": "marcha"}, {"valor": 22, "palabra": "democracia"}, {"valor": 21, "palabra": "porque"}], "MEX - Medios CDMX 2 - TW": [{"valor": 59, "palabra": "méxico"}, {"valor": 54, "palabra": "presidente"}, {"valor": 50, "palabra": "contra"}, {"valor": 40, "palabra": "gobierno"}, {"valor": 30, "palabra": "febrero"}, {"valor": 25, "palabra": "morena"}, {"valor": 24, "palabra": "nacional"}, {"valor": 23, "palabra": "viernes"}, {"valor": 21, "palabra": "mexicano"}, {"valor": 21, "palabra": "muerte"}, {"valor": 20, "palabra": "campaña"}, {"valor": 20, "palabra": "xóchitl"}, {"valor": 20, "palabra": "marcha"}, {"valor": 20, "palabra": "democracia"}, {"valor": 19, "palabra": "estados"}, {"valor": 19, "palabra": "millones"}, {"valor": 19, "palabra": "obrador"}, {"valor": 18, "palabra": "presidencial"}, {"valor": 17, "palabra": "unidos"}, {"valor": 17, "palabra": "gálvez"}, {"valor": 17, "palabra": "francisco"}, {"valor": 16, "palabra": "federal"}, {"valor": 16, "palabra": "prisión"}, {"valor": 16, "palabra": "durante"}, {"valor": 15, "palabra": "dólares"}, {"valor": 15, "palabra": "ardillos"}, {"valor": 15, "palabra": "dinero"}, {"valor": 15, "palabra": "seguridad"}, {"valor": 15, "palabra": "autoridades"}, {"valor": 14, "palabra": "plantas"}, {"valor": 14, "palabra": "información"}, {"valor": 14, "palabra": "estado"}, {"valor": 14, "palabra": "candidata"}, {"valor": 14, "palabra": "trabajadores"}, {"valor": 14, "palabra": "completa"}, {"valor": 13, "palabra": "fueron"}, {"valor": 13, "palabra": "ciudad"}, {"valor": 13, "palabra": "crimen"}, {"valor": 13, "palabra": "organizado"}, {"valor": 13, "palabra": "elecciones"}]}, "2024-02-17-2024-02-17": {"MEX - Influenciadores de Interés - TW": [{"valor": 14, "palabra": "mañana"}, {"valor": 12, "palabra": "presidente"}, {"valor": 11, "palabra": "méxico"}, {"valor": 10, "palabra": "porque"}, {"valor": 9, "palabra": "contra"}, {"valor": 9, "palabra": "democracia"}, {"valor": 8, "palabra": "entrevista"}, {"valor": 8, "palabra": "gracias"}, {"valor": 7, "palabra": "zócalo"}, {"valor": 7, "palabra": "marcha"}, {"valor": 7, "palabra": "abrazo"}, {"valor": 6, "palabra": "revisen"}, {"valor": 6, "palabra": "gobierno"}, {"valor": 6, "palabra": "pendiente"}, {"valor": 5, "palabra": "justicia"}, {"valor": 5, "palabra": "xóchitl"}, {"valor": 5, "palabra": "reporte"}, {"valor": 4, "palabra": "domingo"}, {"valor": 4, "palabra": "marchar"}, {"valor": 4, "palabra": "lluvia"}, {"valor": 4, "palabra": "morena"}, {"valor": 4, "palabra": "dinero"}, {"valor": 4, "palabra": "quiere"}, {"valor": 4, "palabra": "defender"}, {"valor": 4, "palabra": "ciudadanos"}, {"valor": 4, "palabra": "campaña"}, {"valor": 4, "palabra": "verdad"}, {"valor": 4, "palabra": "protección"}, {"valor": 4, "palabra": "régimen"}, {"valor": 4, "palabra": "postura"}, {"valor": 4, "palabra": "alerta"}, {"valor": 3, "palabra": "delitos"}, {"valor": 3, "palabra": "candidata"}, {"valor": 3, "palabra": "nuestro"}, {"valor": 3, "palabra": "director"}, {"valor": 3, "palabra": "federal"}, {"valor": 3, "palabra": "durante"}, {"valor": 3, "palabra": "nacional"}, {"valor": 3, "palabra": "también"}, {"valor": 3, "palabra": "nuestras"}], "MEX - Influenciadores de Interés 2 - TW": [{"valor": 18, "palabra": "porque"}, {"valor": 14, "palabra": "marcha"}, {"valor": 11, "palabra": "cuando"}, {"valor": 11, "palabra": "mañana"}, {"valor": 10, "palabra": "méxico"}, {"valor": 10, "palabra": "democracia"}, {"valor": 9, "palabra": "gobierno"}, {"valor": 8, "palabra": "ciudad"}, {"valor": 8, "palabra": "personas"}, {"valor": 8, "palabra": "contra"}, {"valor": 8, "palabra": "tenemos"}, {"valor": 7, "palabra": "también"}, {"valor": 7, "palabra": "además"}, {"valor": 6, "palabra": "autoridad"}, {"valor": 6, "palabra": "siempre"}, {"valor": 6, "palabra": "fiscalía"}, {"valor": 5, "palabra": "pasado"}, {"valor": 5, "palabra": "causas"}, {"valor": 5, "palabra": "alcaldía"}, {"valor": 5, "palabra": "provocó"}, {"valor": 5, "palabra": "zócalo"}, {"valor": 5, "palabra": "vecinos"}, {"valor": 5, "palabra": "informe"}, {"valor": 5, "palabra": "cualquier"}, {"valor": 5, "palabra": "estamos"}, {"valor": 4, "palabra": "llegar"}, {"valor": 4, "palabra": "documentos"}, {"valor": 4, "palabra": "navalni"}, {"valor": 4, "palabra": "acuerdo"}, {"valor": 4, "palabra": "política"}, {"valor": 4, "palabra": "ciudadanía"}, {"valor": 4, "palabra": "puedes"}, {"valor": 4, "palabra": "países"}, {"valor": 4, "palabra": "libertades"}, {"valor": 4, "palabra": "familia"}, {"valor": 4, "palabra": "quieren"}, {"valor": 4, "palabra": "empresa"}, {"valor": 4, "palabra": "xóchitl"}, {"valor": 4, "palabra": "gálvez"}, {"valor": 4, "palabra": "alerta"}], "MEX - Medios CDMX - TW": [{"valor": 90, "palabra": "méxico"}, {"valor": 64, "palabra": "sábado"}, {"valor": 51, "palabra": "alerta"}, {"valor": 48, "palabra": "contra"}, {"valor": 45, "palabra": "febrero"}, {"valor": 41, "palabra": "detalles"}, {"valor": 40, "palabra": "ciudad"}, {"valor": 38, "palabra": "presidente"}, {"valor": 37, "palabra": "sísmica"}, {"valor": 33, "palabra": "personas"}, {"valor": 32, "palabra": "nacional"}, {"valor": 32, "palabra": "gobierno"}, {"valor": 31, "palabra": "guerrero"}, {"valor": 28, "palabra": "durante"}, {"valor": 27, "palabra": "autoridades"}, {"valor": 24, "palabra": "estado"}, {"valor": 23, "palabra": "seguridad"}, {"valor": 23, "palabra": "semana"}, {"valor": 23, "palabra": "mexicano"}, {"valor": 22, "palabra": "magnitud"}, {"valor": 21, "palabra": "cuando"}, {"valor": 20, "palabra": "opinión"}, {"valor": 19, "palabra": "habitantes"}, {"valor": 19, "palabra": "sheinbaum"}, {"valor": 18, "palabra": "sociales"}, {"valor": 18, "palabra": "estados"}, {"valor": 17, "palabra": "reportan"}, {"valor": 17, "palabra": "historia"}, {"valor": 17, "palabra": "compartimos"}, {"valor": 17, "palabra": "información"}, {"valor": 16, "palabra": "momento"}, {"valor": 16, "palabra": "marcha"}, {"valor": 16, "palabra": "millones"}, {"valor": 16, "palabra": "violencia"}, {"valor": 15, "palabra": "guzmán"}, {"valor": 15, "palabra": "después"}, {"valor": 15, "palabra": "también"}, {"valor": 15, "palabra": "garcía"}, {"valor": 15, "palabra": "acuerdo"}, {"valor": 15, "palabra": "puedes"}], "MEX - Medios CDMX 2 - TW": [{"valor": 46, "palabra": "méxico"}, {"valor": 31, "palabra": "contra"}, {"valor": 25, "palabra": "presidente"}, {"valor": 23, "palabra": "presidencial"}, {"valor": 22, "palabra": "febrero"}, {"valor": 21, "palabra": "gobierno"}, {"valor": 20, "palabra": "estados"}, {"valor": 20, "palabra": "xóchitl"}, {"valor": 19, "palabra": "nacional"}, {"valor": 18, "palabra": "estado"}, {"valor": 18, "palabra": "ciudad"}, {"valor": 17, "palabra": "candidata"}, {"valor": 16, "palabra": "gálvez"}, {"valor": 16, "palabra": "alerta"}, {"valor": 16, "palabra": "magnitud"}, {"valor": 15, "palabra": "unidos"}, {"valor": 15, "palabra": "millones"}, {"valor": 15, "palabra": "durante"}, {"valor": 14, "palabra": "personas"}, {"valor": 14, "palabra": "morena"}, {"valor": 14, "palabra": "sábado"}, {"valor": 14, "palabra": "guerrero"}, {"valor": 12, "palabra": "dólares"}, {"valor": 12, "palabra": "informó"}, {"valor": 12, "palabra": "violencia"}, {"valor": 11, "palabra": "aprehensión"}, {"valor": 11, "palabra": "garcía"}, {"valor": 11, "palabra": "francisco"}, {"valor": 11, "palabra": "muerte"}, {"valor": 11, "palabra": "democracia"}, {"valor": 11, "palabra": "españa"}, {"valor": 11, "palabra": "guerra"}, {"valor": 11, "palabra": "autoridades"}, {"valor": 10, "palabra": "cabeza"}, {"valor": 10, "palabra": "frontera"}, {"valor": 10, "palabra": "obrador"}, {"valor": 10, "palabra": "campaña"}, {"valor": 10, "palabra": "manuel"}, {"valor": 10, "palabra": "mexicana"}, {"valor": 10, "palabra": "además"}]}, "2024-02-18-2024-02-18": {"MEX - Influenciadores de Interés - TW": [{"valor": 26, "palabra": "democracia"}, {"valor": 21, "palabra": "zócalo"}, {"valor": 19, "palabra": "méxico"}, {"valor": 17, "palabra": "contra"}, {"valor": 15, "palabra": "defender"}, {"valor": 15, "palabra": "pueblo"}, {"valor": 14, "palabra": "presidencia"}, {"valor": 12, "palabra": "nuestra"}, {"valor": 12, "palabra": "nacional"}, {"valor": 12, "palabra": "candidata"}, {"valor": 12, "palabra": "nuestro"}, {"valor": 10, "palabra": "presidente"}, {"valor": 9, "palabra": "estamos"}, {"valor": 9, "palabra": "gobierno"}, {"valor": 9, "palabra": "república"}, {"valor": 8, "palabra": "marcha"}, {"valor": 8, "palabra": "ciudadanos"}, {"valor": 8, "palabra": "registro"}, {"valor": 7, "palabra": "cuando"}, {"valor": 7, "palabra": "partido"}, {"valor": 6, "palabra": "morena"}, {"valor": 6, "palabra": "defensa"}, {"valor": 6, "palabra": "claudia"}, {"valor": 6, "palabra": "sheinbaum"}, {"valor": 6, "palabra": "derechos"}, {"valor": 6, "palabra": "elecciones"}, {"valor": 5, "palabra": "derecha"}, {"valor": 5, "palabra": "atiendo"}, {"valor": 5, "palabra": "personas"}, {"valor": 5, "palabra": "electoral"}, {"valor": 5, "palabra": "pública"}, {"valor": 5, "palabra": "coalición"}, {"valor": 5, "palabra": "haciendo"}, {"valor": 5, "palabra": "historia"}, {"valor": 5, "palabra": "gracias"}, {"valor": 5, "palabra": "discurso"}, {"valor": 5, "palabra": "abrazo"}, {"valor": 5, "palabra": "movimiento"}, {"valor": 5, "palabra": "salimos"}, {"valor": 4, "palabra": "mexicanos"}], "MEX - Influenciadores de Interés 2 - TW": [{"valor": 34, "palabra": "democracia"}, {"valor": 31, "palabra": "zócalo"}, {"valor": 26, "palabra": "porque"}, {"valor": 26, "palabra": "méxico"}, {"valor": 23, "palabra": "marcha"}, {"valor": 16, "palabra": "cuando"}, {"valor": 12, "palabra": "presidente"}, {"valor": 11, "palabra": "defensa"}, {"valor": 11, "palabra": "oposición"}, {"valor": 10, "palabra": "bandera"}, {"valor": 9, "palabra": "candidata"}, {"valor": 9, "palabra": "presidencia"}, {"valor": 8, "palabra": "elección"}, {"valor": 8, "palabra": "quienes"}, {"valor": 8, "palabra": "contra"}, {"valor": 8, "palabra": "personas"}, {"valor": 8, "palabra": "lorenzo"}, {"valor": 7, "palabra": "defender"}, {"valor": 7, "palabra": "nuestra"}, {"valor": 7, "palabra": "nacional"}, {"valor": 7, "palabra": "tiempo"}, {"valor": 7, "palabra": "marchar"}, {"valor": 7, "palabra": "córdova"}, {"valor": 7, "palabra": "ciudad"}, {"valor": 6, "palabra": "derrota"}, {"valor": 6, "palabra": "xóchitl"}, {"valor": 6, "palabra": "libertad"}, {"valor": 6, "palabra": "ciudadanía"}, {"valor": 6, "palabra": "registro"}, {"valor": 6, "palabra": "palacio"}, {"valor": 6, "palabra": "también"}, {"valor": 6, "palabra": "quiere"}, {"valor": 6, "palabra": "dictadura"}, {"valor": 6, "palabra": "autoritarismo"}, {"valor": 6, "palabra": "república"}, {"valor": 6, "palabra": "derecho"}, {"valor": 5, "palabra": "constitución"}, {"valor": 5, "palabra": "política"}, {"valor": 5, "palabra": "verdad"}, {"valor": 5, "palabra": "tienen"}], "MEX - Medios CDMX - TW": [{"valor": 138, "palabra": "democracia"}, {"valor": 106, "palabra": "méxico"}, {"valor": 100, "palabra": "marcha"}, {"valor": 81, "palabra": "zócalo"}, {"valor": 57, "palabra": "contra"}, {"valor": 54, "palabra": "personas"}, {"valor": 46, "palabra": "gobierno"}, {"valor": 45, "palabra": "sheinbaum"}, {"valor": 43, "palabra": "córdova"}, {"valor": 42, "palabra": "claudia"}, {"valor": 41, "palabra": "durante"}, {"valor": 41, "palabra": "presidente"}, {"valor": 39, "palabra": "lorenzo"}, {"valor": 38, "palabra": "febrero"}, {"valor": 34, "palabra": "nacional"}, {"valor": 34, "palabra": "domingo"}, {"valor": 32, "palabra": "detalles"}, {"valor": 30, "palabra": "candidata"}, {"valor": 27, "palabra": "ciudad"}, {"valor": 27, "palabra": "discurso"}, {"valor": 25, "palabra": "historia"}, {"valor": 25, "palabra": "nuestra"}, {"valor": 22, "palabra": "ciudadanos"}, {"valor": 22, "palabra": "ciudades"}, {"valor": 22, "palabra": "frente"}, {"valor": 21, "palabra": "electoral"}, {"valor": 21, "palabra": "concentración"}, {"valor": 20, "palabra": "cuando"}, {"valor": 20, "palabra": "presidencial"}, {"valor": 20, "palabra": "accidente"}, {"valor": 20, "palabra": "fueron"}, {"valor": 20, "palabra": "presidencia"}, {"valor": 20, "palabra": "capitalino"}, {"valor": 19, "palabra": "momento"}, {"valor": 19, "palabra": "mexicano"}, {"valor": 18, "palabra": "universal"}, {"valor": 18, "palabra": "conoce"}, {"valor": 18, "palabra": "calles"}, {"valor": 17, "palabra": "autoridades"}, {"valor": 17, "palabra": "seguridad"}], "MEX - Medios CDMX 2 - TW": [{"valor": 66, "palabra": "democracia"}, {"valor": 58, "palabra": "méxico"}, {"valor": 46, "palabra": "presidente"}, {"valor": 46, "palabra": "zócalo"}, {"valor": 41, "palabra": "marcha"}, {"valor": 35, "palabra": "candidata"}, {"valor": 31, "palabra": "presidencial"}, {"valor": 31, "palabra": "gobierno"}, {"valor": 29, "palabra": "sheinbaum"}, {"valor": 27, "palabra": "córdova"}, {"valor": 25, "palabra": "nacional"}, {"valor": 24, "palabra": "claudia"}, {"valor": 23, "palabra": "lorenzo"}, {"valor": 22, "palabra": "personas"}, {"valor": 21, "palabra": "ciudad"}, {"valor": 20, "palabra": "domingo"}, {"valor": 20, "palabra": "obrador"}, {"valor": 20, "palabra": "contra"}, {"valor": 19, "palabra": "morena"}, {"valor": 18, "palabra": "febrero"}, {"valor": 18, "palabra": "durante"}, {"valor": 16, "palabra": "frente"}, {"valor": 16, "palabra": "concentración"}, {"valor": 15, "palabra": "registro"}, {"valor": 15, "palabra": "asistentes"}, {"valor": 13, "palabra": "xóchitl"}, {"valor": 13, "palabra": "partido"}, {"valor": 13, "palabra": "autoridades"}, {"valor": 12, "palabra": "también"}, {"valor": 12, "palabra": "estado"}, {"valor": 12, "palabra": "mexicano"}, {"valor": 12, "palabra": "nuestra"}, {"valor": 11, "palabra": "mexicana"}, {"valor": 11, "palabra": "manuel"}, {"valor": 11, "palabra": "defender"}, {"valor": 11, "palabra": "campaña"}, {"valor": 11, "palabra": "guerra"}, {"valor": 11, "palabra": "mensaje"}, {"valor": 11, "palabra": "discurso"}, {"valor": 11, "palabra": "defensa"}]}, "2024-02-19-2024-02-19": {"MEX - Influenciadores de Interés - TW": [{"valor": 8, "palabra": "zócalo"}, {"valor": 8, "palabra": "democracia"}, {"valor": 8, "palabra": "presidente"}, {"valor": 7, "palabra": "gobierno"}, {"valor": 6, "palabra": "marcha"}, {"valor": 5, "palabra": "cuando"}, {"valor": 5, "palabra": "méxico"}, {"valor": 4, "palabra": "abrazo"}, {"valor": 4, "palabra": "columna"}, {"valor": 4, "palabra": "gracias"}, {"valor": 3, "palabra": "ciudadanos"}, {"valor": 3, "palabra": "porque"}, {"valor": 3, "palabra": "trenes"}, {"valor": 3, "palabra": "pasajeros"}, {"valor": 3, "palabra": "nacional"}, {"valor": 3, "palabra": "morena"}, {"valor": 3, "palabra": "demócratas"}, {"valor": 3, "palabra": "fraudes"}, {"valor": 3, "palabra": "electorales"}, {"valor": 3, "palabra": "manuel"}, {"valor": 3, "palabra": "también"}, {"valor": 3, "palabra": "bartlett"}, {"valor": 3, "palabra": "defensa"}, {"valor": 3, "palabra": "pretende"}, {"valor": 2, "palabra": "difundan"}, {"valor": 2, "palabra": "entrevista"}, {"valor": 2, "palabra": "completa"}, {"valor": 2, "palabra": "piensa"}, {"valor": 2, "palabra": "pueblo"}, {"valor": 2, "palabra": "justicia"}, {"valor": 2, "palabra": "iglesia"}, {"valor": 2, "palabra": "enorme"}, {"valor": 2, "palabra": "fuerza"}, {"valor": 2, "palabra": "tienen"}, {"valor": 2, "palabra": "nosotros"}, {"valor": 2, "palabra": "seguridad"}, {"valor": 2, "palabra": "verdad"}, {"valor": 2, "palabra": "regresar"}, {"valor": 2, "palabra": "candidata"}, {"valor": 2, "palabra": "esperanza"}], "MEX - Influenciadores de Interés 2 - TW": [{"valor": 3, "palabra": "democracia"}, {"valor": 2, "palabra": "debería"}, {"valor": 2, "palabra": "libertades"}, {"valor": 2, "palabra": "quienes"}, {"valor": 2, "palabra": "dictadura"}, {"valor": 2, "palabra": "gobernar"}, {"valor": 2, "palabra": "autoritaria"}, {"valor": 1, "palabra": "comparto"}, {"valor": 1, "palabra": "resumen"}, {"valor": 1, "palabra": "actividades"}, {"valor": 1, "palabra": "semana"}, {"valor": 1, "palabra": "nominarías"}, {"valor": 1, "palabra": "premio"}, {"valor": 1, "palabra": "presidente"}, {"valor": 1, "palabra": "obrador"}, {"valor": 1, "palabra": "entendiste"}, {"valor": 1, "palabra": "parece"}, {"valor": 1, "palabra": "diablo"}, {"valor": 1, "palabra": "hicieran"}, {"valor": 1, "palabra": "película"}, {"valor": 1, "palabra": "guzmán"}, {"valor": 1, "palabra": "convirtiera"}, {"valor": 1, "palabra": "padrino"}, {"valor": 1, "palabra": "mexicano"}, {"valor": 1, "palabra": "dirigirla"}, {"valor": 1, "palabra": "méxico"}, {"valor": 1, "palabra": "doctrinada"}, {"valor": 1, "palabra": "estrada"}, {"valor": 1, "palabra": "doctrina"}, {"valor": 1, "palabra": "intelectual"}, {"valor": 1, "palabra": "prestes"}, {"valor": 1, "palabra": "importancia"}, {"valor": 1, "palabra": "argumento"}, {"valor": 1, "palabra": "bananero"}, {"valor": 1, "palabra": "encabezado"}, {"valor": 1, "palabra": "beltrán"}, {"valor": 1, "palabra": "hablando"}, {"valor": 1, "palabra": "corrupción"}, {"valor": 1, "palabra": "trabajar"}, {"valor": 1, "palabra": "gonzalo"}], "MEX - Medios CDMX - TW": [{"valor": 63, "palabra": "méxico"}, {"valor": 49, "palabra": "democracia"}, {"valor": 45, "palabra": "presidente"}, {"valor": 39, "palabra": "marcha"}, {"valor": 35, "palabra": "febrero"}, {"valor": 31, "palabra": "gobierno"}, {"valor": 26, "palabra": "contra"}, {"valor": 26, "palabra": "escribe"}, {"valor": 24, "palabra": "durante"}, {"valor": 22, "palabra": "mexicano"}, {"valor": 21, "palabra": "personas"}, {"valor": 20, "palabra": "opinión"}, {"valor": 17, "palabra": "estado"}, {"valor": 17, "palabra": "domingo"}, {"valor": 17, "palabra": "puebla"}, {"valor": 17, "palabra": "nuestra"}, {"valor": 16, "palabra": "obrador"}, {"valor": 15, "palabra": "huelga"}, {"valor": 15, "palabra": "fueron"}, {"valor": 15, "palabra": "zócalo"}, {"valor": 15, "palabra": "ciudad"}, {"valor": 14, "palabra": "también"}, {"valor": 14, "palabra": "cuando"}, {"valor": 14, "palabra": "sheinbaum"}, {"valor": 14, "palabra": "ejército"}, {"valor": 13, "palabra": "autoridades"}, {"valor": 13, "palabra": "violencia"}, {"valor": 13, "palabra": "candidata"}, {"valor": 12, "palabra": "conoce"}, {"valor": 12, "palabra": "trabajadores"}, {"valor": 12, "palabra": "porque"}, {"valor": 12, "palabra": "presidencial"}, {"valor": 11, "palabra": "decimos"}, {"valor": 11, "palabra": "información"}, {"valor": 11, "palabra": "hombre"}, {"valor": 11, "palabra": "millones"}, {"valor": 11, "palabra": "semana"}, {"valor": 11, "palabra": "claudia"}, {"valor": 11, "palabra": "portada"}, {"valor": 11, "palabra": "pueblo"}], "MEX - Medios CDMX 2 - TW": [{"valor": 43, "palabra": "democracia"}, {"valor": 35, "palabra": "presidente"}, {"valor": 30, "palabra": "contra"}, {"valor": 26, "palabra": "méxico"}, {"valor": 26, "palabra": "marcha"}, {"valor": 16, "palabra": "gobierno"}, {"valor": 16, "palabra": "completa"}, {"valor": 15, "palabra": "puebla"}, {"valor": 15, "palabra": "opinión"}, {"valor": 12, "palabra": "pueblo"}, {"valor": 11, "palabra": "presidencial"}, {"valor": 11, "palabra": "febrero"}, {"valor": 11, "palabra": "zócalo"}, {"valor": 11, "palabra": "defensa"}, {"valor": 11, "palabra": "nacional"}, {"valor": 10, "palabra": "mexicano"}, {"valor": 10, "palabra": "claudia"}, {"valor": 10, "palabra": "sheinbaum"}, {"valor": 10, "palabra": "opositores"}, {"valor": 10, "palabra": "aseguró"}, {"valor": 9, "palabra": "israel"}, {"valor": 9, "palabra": "domingo"}, {"valor": 9, "palabra": "afirmó"}, {"valor": 9, "palabra": "autoridades"}, {"valor": 8, "palabra": "asistentes"}, {"valor": 8, "palabra": "electoral"}, {"valor": 8, "palabra": "córdova"}, {"valor": 8, "palabra": "huelga"}, {"valor": 8, "palabra": "personas"}, {"valor": 8, "palabra": "fraudes"}, {"valor": 8, "palabra": "senado"}, {"valor": 8, "palabra": "muertos"}, {"valor": 8, "palabra": "obrador"}, {"valor": 8, "palabra": "estado"}, {"valor": 8, "palabra": "corrupción"}, {"valor": 8, "palabra": "nuestra"}, {"valor": 7, "palabra": "candidata"}, {"valor": 7, "palabra": "hombre"}, {"valor": 7, "palabra": "partido"}, {"valor": 7, "palabra": "primera"}]}}