{"2024-02-05-2024-02-05": [[{"color": "#97c2fc", "size": 10, "id": "MEX - Influenciadores de Interés 2 - TW", "label": "MEX - Influenciadores de Interés 2 - TW", "shape": "dot", "font": {"color": "white"}}, {"color": "#97c2fc", "size": 10, "id": "presidente", "label": "presidente", "shape": "dot", "font": {"color": "white"}}, {"color": "#97c2fc", "size": 10, "id": "constitución", "label": "constitución", "shape": "dot", "font": {"color": "white"}}, {"color": "#97c2fc", "size": 10, "id": "cuando", "label": "cuando", "shape": "dot", "font": {"color": "white"}}, {"color": "#97c2fc", "size": 10, "id": "contra", "label": "contra", "shape": "dot", "font": {"color": "white"}}, {"color": "#97c2fc", "size": 10, "id": "gracias", "label": "gracias", "shape": "dot", "font": {"color": "white"}}, {"color": "#97c2fc", "size": 10, "id": "porque", "label": "porque", "shape": "dot", "font": {"color": "white"}}, {"color": "#97c2fc", "size": 10, "id": "méxico", "label": "méxico", "shape": "dot", "font": {"color": "white"}}, {"color": "#97c2fc", "size": 10, "id": "gobierno", "label": "gobierno", "shape": "dot", "font": {"color": "white"}}, {"color": "#97c2fc", "size": 10, "id": "obrador", "label": "obrador", "shape": "dot", "font": {"color": "white"}}, {"color": "#97c2fc", "size": 10, "id": "nuestra", "label": "nuestra", "shape": "dot", "font": {"color": "white"}}, {"color": "#97c2fc", "size": 10, "id": "reformas", "label": "reformas", "shape": "dot", "font": {"color": "white"}}, {"color": "#97c2fc", "size": 10, "id": "verdad", "label": "verdad", "shape": "dot", "font": {"color": "white"}}, {"color": "#97c2fc", "size": 10, "id": "resultados", "label": "resultados", "shape": "dot", "font": {"color": "white"}}, {"color": "#97c2fc", "size": 10, "id": "cáncer", "label": "cáncer", "shape": "dot", "font": {"color": "white"}}, {"color": "#97c2fc", "size": 10, "id": "estado", "label": "estado", "shape": "dot", "font": {"color": "white"}}, {"color": "#97c2fc", "size": 10, "id": "mollinedo", "label": "mollinedo", "shape": "dot", "font": {"color": "white"}}, {"color": "#97c2fc", "size": 10, "id": "también", "label": "también", "shape": "dot", "font": {"color": "white"}}, {"color": "#97c2fc", "size": 10, "id": "ustedes", "label": "ustedes", "shape": "dot", "font": {"color": "white"}}, {"color": "#97c2fc", "size": 10, "id": "trabajo", "label": "trabajo", "shape": "dot", "font": {"color": "white"}}, {"color": "#97c2fc", "size": 10, "id": "morena", "label": "morena", "shape": "dot", "font": {"color": "white"}}, {"color": "#97c2fc", "size": 10, "id": "elección", "label": "elección", "shape": "dot", "font": {"color": "white"}}, {"color": "#97c2fc", "size": 10, "id": "ciudadanos", "label": "ciudadanos", "shape": "dot", "font": {"color": "white"}}, {"color": "#97c2fc", "size": 10, "id": "xóchitl", "label": "xóchitl", "shape": "dot", "font": {"color": "white"}}, {"color": "#97c2fc", "size": 10, "id": "quiere", "label": "quiere", "shape": "dot", "font": {"color": "white"}}, {"color": "#97c2fc", "size": 10, "id": "oposición", "label": "oposición", "shape": "dot", "font": {"color": "white"}}, {"color": "#97c2fc", "size": 10, "id": "dinero", "label": "dinero", "shape": "dot", "font": {"color": "white"}}, {"color": "#97c2fc", "size": 10, "id": "social", "label": "social", "shape": "dot", "font": {"color": "white"}}, {"color": "#97c2fc", "size": 10, "id": "abrazo", "label": "abrazo", "shape": "dot", "font": {"color": "white"}}, {"color": "#97c2fc", "size": 10, "id": "mujeres", "label": "mujeres", "shape": "dot", "font": {"color": "white"}}, {"color": "#97c2fc", "size": 10, "id": "vecinos", "label": "vecinos", "shape": "dot", "font": {"color": "white"}}, {"color": "#97c2fc", "size": 10, "id": "MEX - Medios CDMX - TW", "label": "MEX - Medios CDMX - TW", "shape": "dot", "font": {"color": "white"}}, {"color": "#97c2fc", "size": 10, "id": "MEX - Medios CDMX 2 - TW", "label": "MEX - Medios CDMX 2 - TW", "shape": "dot", "font": {"color": "white"}}, {"color": "#97c2fc", "size": 10, "id": "MEX - Influenciadores de Interés - TW", "label": "MEX - Influenciadores de Interés - TW", "shape": "dot", "font": {"color": "white"}}, {"color": "#97c2fc", "size": 10, "id": "febrero", "label": "febrero", "shape": "dot", "font": {"color": "white"}}, {"color": "#97c2fc", "size": 10, "id": "personas", "label": "personas", "shape": "dot", "font": {"color": "white"}}, {"color": "#97c2fc", "size": 10, "id": "durante", "label": "durante", "shape": "dot", "font": {"color": "white"}}, {"color": "#97c2fc", "size": 10, "id": "reforma", "label": "reforma", "shape": "dot", "font": {"color": "white"}}, {"color": "#97c2fc", "size": 10, "id": "nacional", "label": "nacional", "shape": "dot", "font": {"color": "white"}}, {"color": "#97c2fc", "size": 10, "id": "paquete", "label": "paquete", "shape": "dot", "font": {"color": "white"}}, {"color": "#97c2fc", "size": 10, "id": "carlos", "label": "carlos", "shape": "dot", "font": {"color": "white"}}, {"color": "#97c2fc", "size": 10, "id": "bukele", "label": "bukele", "shape": "dot", "font": {"color": "white"}}, {"color": "#97c2fc", "size": 10, "id": "iniciativas", "label": "iniciativas", "shape": "dot", "font": {"color": "white"}}, {"color": "#97c2fc", "size": 10, "id": "grammy", "label": "grammy", "shape": "dot", "font": {"color": "white"}}, {"color": "#97c2fc", "size": 10, "id": "frontera", "label": "frontera", "shape": "dot", "font": {"color": "white"}}, {"color": "#97c2fc", "size": 10, "id": "seguridad", "label": "seguridad", "shape": "dot", "font": {"color": "white"}}, {"color": "#97c2fc", "size": 10, "id": "cuatro", "label": "cuatro", "shape": "dot", "font": {"color": "white"}}, {"color": "#97c2fc", "size": 10, "id": "transportistas", "label": "transportistas", "shape": "dot", "font": {"color": "white"}}, {"color": "#97c2fc", "size": 10, "id": "cuenta", "label": "cuenta", "shape": "dot", "font": {"color": "white"}}, {"color": "#97c2fc", "size": 10, "id": "historia", "label": "historia", "shape": "dot", "font": {"color": "white"}}, {"color": "#97c2fc", "size": 10, "id": "taylor", "label": "taylor", "shape": "dot", "font": {"color": "white"}}, {"color": "#97c2fc", "size": 10, "id": "mundial", "label": "mundial", "shape": "dot", "font": {"color": "white"}}, {"color": "#97c2fc", "size": 10, "id": "constitucionales", "label": "constitucionales", "shape": "dot", "font": {"color": "white"}}, {"color": "#97c2fc", "size": 10, "id": "palacio", "label": "palacio", "shape": "dot", "font": {"color": "white"}}, {"color": "#97c2fc", "size": 10, "id": "incendios", "label": "incendios", "shape": "dot", "font": {"color": "white"}}, {"color": "#97c2fc", "size": 10, "id": "completa", "label": "completa", "shape": "dot", "font": {"color": "white"}}, {"color": "#97c2fc", "size": 10, "id": "estados", "label": "estados", "shape": "dot", "font": {"color": "white"}}, {"color": "#97c2fc", "size": 10, "id": "acuerdo", "label": "acuerdo", "shape": "dot", "font": {"color": "white"}}, {"color": "#97c2fc", "size": 10, "id": "millones", "label": "millones", "shape": "dot", "font": {"color": "white"}}, {"color": "#97c2fc", "size": 10, "id": "ciudad", "label": "ciudad", "shape": "dot", "font": {"color": "white"}}, {"color": "#97c2fc", "size": 10, "id": "pensiones", "label": "pensiones", "shape": "dot", "font": {"color": "white"}}, {"color": "#97c2fc", "size": 10, "id": "violencia", "label": "violencia", "shape": "dot", "font": {"color": "white"}}, {"color": "#97c2fc", "size": 10, "id": "electoral", "label": "electoral", "shape": "dot", "font": {"color": "white"}}, {"color": "#97c2fc", "size": 10, "id": "judicial", "label": "judicial", "shape": "dot", "font": {"color": "white"}}, {"color": "#97c2fc", "size": 10, "id": "política", "label": "política", "shape": "dot", "font": {"color": "white"}}, {"color": "#97c2fc", "size": 10, "id": "pueblo", "label": "pueblo", "shape": "dot", "font": {"color": "white"}}, {"color": "#97c2fc", "size": 10, "id": "elecciones", "label": "elecciones", "shape": "dot", "font": {"color": "white"}}, {"color": "#97c2fc", "size": 10, "id": "mayoría", "label": "mayoría", "shape": "dot", "font": {"color": "white"}}, {"color": "#97c2fc", "size": 10, "id": "salario", "label": "salario", "shape": "dot", "font": {"color": "white"}}, {"color": "#97c2fc", "size": 10, "id": "momento", "label": "momento", "shape": "dot", "font": {"color": "white"}}, {"color": "#97c2fc", "size": 10, "id": "ejecutivo", "label": "ejecutivo", "shape": "dot", "font": {"color": "white"}}, {"color": "#97c2fc", "size": 10, "id": "electorales", "label": "electorales", "shape": "dot", "font": {"color": "white"}}, {"color": "#97c2fc", "size": 10, "id": "políticos", "label": "políticos", "shape": "dot", "font": {"color": "white"}}], [{"Frecuencia": 25, "value": 0.2840909090909091, "width": 0.2840909090909091, "length": 3.5199999999999996, "from": "MEX - Influenciadores de Interés 2 - TW", "to": "presidente"}, {"Frecuencia": 21, "value": 0.23863636363636365, "width": 0.23863636363636365, "length": 4.190476190476191, "from": "MEX - Influenciadores de Interés 2 - TW", "to": "constitución"}, {"Frecuencia": 20, "value": 0.22727272727272727, "width": 0.22727272727272727, "length": 4.4, "from": "MEX - Influenciadores de Interés 2 - TW", "to": "cuando"}, {"Frecuencia": 15, "value": 0.17045454545454544, "width": 0.17045454545454544, "length": 5.866666666666667, "from": "MEX - Influenciadores de Interés 2 - TW", "to": "contra"}, {"Frecuencia": 14, "value": 0.1590909090909091, "width": 0.1590909090909091, "length": 6.285714285714286, "from": "MEX - Influenciadores de Interés 2 - TW", "to": "gracias"}, {"Frecuencia": 12, "value": 0.13636363636363635, "width": 0.13636363636363635, "length": 7.333333333333334, "from": "MEX - Influenciadores de Interés 2 - TW", "to": "porque"}, {"Frecuencia": 11, "value": 0.125, "width": 0.125, "length": 8.0, "from": "MEX - Influenciadores de Interés 2 - TW", "to": "méxico"}, {"Frecuencia": 11, "value": 0.125, "width": 0.125, "length": 8.0, "from": "MEX - Influenciadores de Interés 2 - TW", "to": "gobierno"}, {"Frecuencia": 10, "value": 0.11363636363636363, "width": 0.11363636363636363, "length": 8.8, "from": "MEX - Influenciadores de Interés 2 - TW", "to": "obrador"}, {"Frecuencia": 8, "value": 0.09090909090909091, "width": 0.09090909090909091, "length": 11.0, "from": "MEX - Influenciadores de Interés 2 - TW", "to": "nuestra"}, {"Frecuencia": 7, "value": 0.07954545454545454, "width": 0.07954545454545454, "length": 12.571428571428571, "from": "MEX - Influenciadores de Interés 2 - TW", "to": "reformas"}, {"Frecuencia": 7, "value": 0.07954545454545454, "width": 0.07954545454545454, "length": 12.571428571428571, "from": "MEX - Influenciadores de Interés 2 - TW", "to": "verdad"}, {"Frecuencia": 7, "value": 0.07954545454545454, "width": 0.07954545454545454, "length": 12.571428571428571, "from": "MEX - Influenciadores de Interés 2 - TW", "to": "resultados"}, {"Frecuencia": 7, "value": 0.07954545454545454, "width": 0.07954545454545454, "length": 12.571428571428571, "from": "MEX - Influenciadores de Interés 2 - TW", "to": "cáncer"}, {"Frecuencia": 7, "value": 0.07954545454545454, "width": 0.07954545454545454, "length": 12.571428571428571, "from": "MEX - Influenciadores de Interés 2 - TW", "to": "estado"}, {"Frecuencia": 7, "value": 0.07954545454545454, "width": 0.07954545454545454, "length": 12.571428571428571, "from": "MEX - Influenciadores de Interés 2 - TW", "to": "mollinedo"}, {"Frecuencia": 6, "value": 0.06818181818181818, "width": 0.06818181818181818, "length": 14.666666666666668, "from": "MEX - Influenciadores de Interés 2 - TW", "to": "también"}, {"Frecuencia": 6, "value": 0.06818181818181818, "width": 0.06818181818181818, "length": 14.666666666666668, "from": "MEX - Influenciadores de Interés 2 - TW", "to": "ustedes"}, {"Frecuencia": 6, "value": 0.06818181818181818, "width": 0.06818181818181818, "length": 14.666666666666668, "from": "MEX - Influenciadores de Interés 2 - TW", "to": "trabajo"}, {"Frecuencia": 6, "value": 0.06818181818181818, "width": 0.06818181818181818, "length": 14.666666666666668, "from": "MEX - Influenciadores de Interés 2 - TW", "to": "morena"}, {"Frecuencia": 6, "value": 0.06818181818181818, "width": 0.06818181818181818, "length": 14.666666666666668, "from": "MEX - Influenciadores de Interés 2 - TW", "to": "elección"}, {"Frecuencia": 6, "value": 0.06818181818181818, "width": 0.06818181818181818, "length": 14.666666666666668, "from": "MEX - Influenciadores de Interés 2 - TW", "to": "ciudadanos"}, {"Frecuencia": 6, "value": 0.06818181818181818, "width": 0.06818181818181818, "length": 14.666666666666668, "from": "MEX - Influenciadores de Interés 2 - TW", "to": "xóchitl"}, {"Frecuencia": 6, "value": 0.06818181818181818, "width": 0.06818181818181818, "length": 14.666666666666668, "from": "MEX - Influenciadores de Interés 2 - TW", "to": "quiere"}, {"Frecuencia": 6, "value": 0.06818181818181818, "width": 0.06818181818181818, "length": 14.666666666666668, "from": "MEX - Influenciadores de Interés 2 - TW", "to": "oposición"}, {"Frecuencia": 6, "value": 0.06818181818181818, "width": 0.06818181818181818, "length": 14.666666666666668, "from": "MEX - Influenciadores de Interés 2 - TW", "to": "dinero"}, {"Frecuencia": 6, "value": 0.06818181818181818, "width": 0.06818181818181818, "length": 14.666666666666668, "from": "MEX - Influenciadores de Interés 2 - TW", "to": "social"}, {"Frecuencia": 5, "value": 0.056818181818181816, "width": 0.056818181818181816, "length": 17.6, "from": "MEX - Influenciadores de Interés 2 - TW", "to": "abrazo"}, {"Frecuencia": 5, "value": 0.056818181818181816, "width": 0.056818181818181816, "length": 17.6, "from": "MEX - Influenciadores de Interés 2 - TW", "to": "mujeres"}, {"Frecuencia": 5, "value": 0.056818181818181816, "width": 0.056818181818181816, "length": 17.6, "from": "MEX - Influenciadores de Interés 2 - TW", "to": "vecinos"}, {"Frecuencia": 77, "value": 0.875, "width": 0.875, "length": 1.1428571428571428, "from": "presidente", "to": "MEX - Medios CDMX - TW"}, {"Frecuencia": 85, "value": 0.9659090909090909, "width": 0.9659090909090909, "length": 1.0352941176470587, "from": "presidente", "to": "MEX - Medios CDMX 2 - TW"}, {"Frecuencia": 28, "value": 0.3181818181818182, "width": 0.3181818181818182, "length": 3.142857142857143, "from": "presidente", "to": "MEX - Influenciadores de Interés - TW"}, {"Frecuencia": 44, "value": 0.5, "width": 0.5, "length": 2.0, "from": "constitución", "to": "MEX - Medios CDMX - TW"}, {"Frecuencia": 39, "value": 0.4431818181818182, "width": 0.4431818181818182, "length": 2.2564102564102564, "from": "constitución", "to": "MEX - Medios CDMX 2 - TW"}, {"Frecuencia": 24, "value": 0.2727272727272727, "width": 0.2727272727272727, "length": 3.666666666666667, "from": "constitución", "to": "MEX - Influenciadores de Interés - TW"}, {"Frecuencia": 52, "value": 0.5909090909090909, "width": 0.5909090909090909, "length": 1.6923076923076923, "from": "contra", "to": "MEX - Medios CDMX - TW"}, {"Frecuencia": 46, "value": 0.5227272727272727, "width": 0.5227272727272727, "length": 1.9130434782608696, "from": "contra", "to": "MEX - Medios CDMX 2 - TW"}, {"Frecuencia": 12, "value": 0.13636363636363635, "width": 0.13636363636363635, "length": 7.333333333333334, "from": "contra", "to": "MEX - Influenciadores de Interés - TW"}, {"Frecuencia": 8, "value": 0.09090909090909091, "width": 0.09090909090909091, "length": 11.0, "from": "porque", "to": "MEX - Influenciadores de Interés - TW"}, {"Frecuencia": 88, "value": 1.0, "width": 1.0, "length": 1.0, "from": "méxico", "to": "MEX - Medios CDMX - TW"}, {"Frecuencia": 74, "value": 0.8409090909090909, "width": 0.8409090909090909, "length": 1.1891891891891893, "from": "méxico", "to": "MEX - Medios CDMX 2 - TW"}, {"Frecuencia": 14, "value": 0.1590909090909091, "width": 0.1590909090909091, "length": 6.285714285714286, "from": "méxico", "to": "MEX - Influenciadores de Interés - TW"}, {"Frecuencia": 37, "value": 0.42045454545454547, "width": 0.42045454545454547, "length": 2.3783783783783785, "from": "gobierno", "to": "MEX - Medios CDMX - TW"}, {"Frecuencia": 23, "value": 0.26136363636363635, "width": 0.26136363636363635, "length": 3.8260869565217392, "from": "gobierno", "to": "MEX - Medios CDMX 2 - TW"}, {"Frecuencia": 9, "value": 0.10227272727272728, "width": 0.10227272727272728, "length": 9.777777777777777, "from": "gobierno", "to": "MEX - Influenciadores de Interés - TW"}, {"Frecuencia": 33, "value": 0.375, "width": 0.375, "length": 2.6666666666666665, "from": "obrador", "to": "MEX - Medios CDMX - TW"}, {"Frecuencia": 23, "value": 0.26136363636363635, "width": 0.26136363636363635, "length": 3.8260869565217392, "from": "obrador", "to": "MEX - Medios CDMX 2 - TW"}, {"Frecuencia": 8, "value": 0.09090909090909091, "width": 0.09090909090909091, "length": 11.0, "from": "obrador", "to": "MEX - Influenciadores de Interés - TW"}, {"Frecuencia": 8, "value": 0.09090909090909091, "width": 0.09090909090909091, "length": 11.0, "from": "nuestra", "to": "MEX - Influenciadores de Interés - TW"}, {"Frecuencia": 78, "value": 0.8863636363636364, "width": 0.8863636363636364, "length": 1.1282051282051282, "from": "reformas", "to": "MEX - Medios CDMX - TW"}, {"Frecuencia": 58, "value": 0.6590909090909091, "width": 0.6590909090909091, "length": 1.517241379310345, "from": "reformas", "to": "MEX - Medios CDMX 2 - TW"}, {"Frecuencia": 37, "value": 0.42045454545454547, "width": 0.42045454545454547, "length": 2.3783783783783785, "from": "reformas", "to": "MEX - Influenciadores de Interés - TW"}, {"Frecuencia": 35, "value": 0.3977272727272727, "width": 0.3977272727272727, "length": 2.5142857142857142, "from": "cáncer", "to": "MEX - Medios CDMX - TW"}, {"Frecuencia": 18, "value": 0.20454545454545456, "width": 0.20454545454545456, "length": 4.888888888888888, "from": "cáncer", "to": "MEX - Medios CDMX 2 - TW"}, {"Frecuencia": 30, "value": 0.3409090909090909, "width": 0.3409090909090909, "length": 2.9333333333333336, "from": "estado", "to": "MEX - Medios CDMX - TW"}, {"Frecuencia": 8, "value": 0.09090909090909091, "width": 0.09090909090909091, "length": 11.0, "from": "estado", "to": "MEX - Influenciadores de Interés - TW"}, {"Frecuencia": 6, "value": 0.06818181818181818, "width": 0.06818181818181818, "length": 14.666666666666668, "from": "también", "to": "MEX - Influenciadores de Interés - TW"}, {"Frecuencia": 7, "value": 0.07954545454545454, "width": 0.07954545454545454, "length": 12.571428571428571, "from": "morena", "to": "MEX - Influenciadores de Interés - TW"}, {"Frecuencia": 21, "value": 0.23863636363636365, "width": 0.23863636363636365, "length": 4.190476190476191, "from": "xóchitl", "to": "MEX - Medios CDMX 2 - TW"}, {"Frecuencia": 6, "value": 0.06818181818181818, "width": 0.06818181818181818, "length": 14.666666666666668, "from": "quiere", "to": "MEX - Influenciadores de Interés - TW"}, {"Frecuencia": 13, "value": 0.14772727272727273, "width": 0.14772727272727273, "length": 6.769230769230769, "from": "oposición", "to": "MEX - Influenciadores de Interés - TW"}, {"Frecuencia": 8, "value": 0.09090909090909091, "width": 0.09090909090909091, "length": 11.0, "from": "abrazo", "to": "MEX - Influenciadores de Interés - TW"}, {"Frecuencia": 61, "value": 0.6931818181818182, "width": 0.6931818181818182, "length": 1.442622950819672, "from": "MEX - Medios CDMX - TW", "to": "febrero"}, {"Frecuencia": 50, "value": 0.5681818181818182, "width": 0.5681818181818182, "length": 1.7599999999999998, "from": "MEX - Medios CDMX - TW", "to": "personas"}, {"Frecuencia": 47, "value": 0.5340909090909091, "width": 0.5340909090909091, "length": 1.872340425531915, "from": "MEX - Medios CDMX - TW", "to": "durante"}, {"Frecuencia": 45, "value": 0.5113636363636364, "width": 0.5113636363636364, "length": 1.9555555555555555, "from": "MEX - Medios CDMX - TW", "to": "reforma"}, {"Frecuencia": 43, "value": 0.48863636363636365, "width": 0.48863636363636365, "length": 2.046511627906977, "from": "MEX - Medios CDMX - TW", "to": "nacional"}, {"Frecuencia": 37, "value": 0.42045454545454547, "width": 0.42045454545454547, "length": 2.3783783783783785, "from": "MEX - Medios CDMX - TW", "to": "paquete"}, {"Frecuencia": 34, "value": 0.38636363636363635, "width": 0.38636363636363635, "length": 2.588235294117647, "from": "MEX - Medios CDMX - TW", "to": "carlos"}, {"Frecuencia": 32, "value": 0.36363636363636365, "width": 0.36363636363636365, "length": 2.75, "from": "MEX - Medios CDMX - TW", "to": "bukele"}, {"Frecuencia": 32, "value": 0.36363636363636365, "width": 0.36363636363636365, "length": 2.75, "from": "MEX - Medios CDMX - TW", "to": "iniciativas"}, {"Frecuencia": 27, "value": 0.3068181818181818, "width": 0.3068181818181818, "length": 3.259259259259259, "from": "MEX - Medios CDMX - TW", "to": "grammy"}, {"Frecuencia": 27, "value": 0.3068181818181818, "width": 0.3068181818181818, "length": 3.259259259259259, "from": "MEX - Medios CDMX - TW", "to": "frontera"}, {"Frecuencia": 27, "value": 0.3068181818181818, "width": 0.3068181818181818, "length": 3.259259259259259, "from": "MEX - Medios CDMX - TW", "to": "seguridad"}, {"Frecuencia": 27, "value": 0.3068181818181818, "width": 0.3068181818181818, "length": 3.259259259259259, "from": "MEX - Medios CDMX - TW", "to": "cuatro"}, {"Frecuencia": 27, "value": 0.3068181818181818, "width": 0.3068181818181818, "length": 3.259259259259259, "from": "MEX - Medios CDMX - TW", "to": "transportistas"}, {"Frecuencia": 26, "value": 0.29545454545454547, "width": 0.29545454545454547, "length": 3.3846153846153846, "from": "MEX - Medios CDMX - TW", "to": "cuenta"}, {"Frecuencia": 25, "value": 0.2840909090909091, "width": 0.2840909090909091, "length": 3.5199999999999996, "from": "MEX - Medios CDMX - TW", "to": "historia"}, {"Frecuencia": 23, "value": 0.26136363636363635, "width": 0.26136363636363635, "length": 3.8260869565217392, "from": "MEX - Medios CDMX - TW", "to": "taylor"}, {"Frecuencia": 23, "value": 0.26136363636363635, "width": 0.26136363636363635, "length": 3.8260869565217392, "from": "MEX - Medios CDMX - TW", "to": "mundial"}, {"Frecuencia": 23, "value": 0.26136363636363635, "width": 0.26136363636363635, "length": 3.8260869565217392, "from": "MEX - Medios CDMX - TW", "to": "constitucionales"}, {"Frecuencia": 22, "value": 0.25, "width": 0.25, "length": 4.0, "from": "MEX - Medios CDMX - TW", "to": "palacio"}, {"Frecuencia": 22, "value": 0.25, "width": 0.25, "length": 4.0, "from": "MEX - Medios CDMX - TW", "to": "incendios"}, {"Frecuencia": 18, "value": 0.20454545454545456, "width": 0.20454545454545456, "length": 4.888888888888888, "from": "febrero", "to": "MEX - Medios CDMX 2 - TW"}, {"Frecuencia": 19, "value": 0.2159090909090909, "width": 0.2159090909090909, "length": 4.631578947368421, "from": "personas", "to": "MEX - Medios CDMX 2 - TW"}, {"Frecuencia": 16, "value": 0.18181818181818182, "width": 0.18181818181818182, "length": 5.5, "from": "durante", "to": "MEX - Medios CDMX 2 - TW"}, {"Frecuencia": 19, "value": 0.2159090909090909, "width": 0.2159090909090909, "length": 4.631578947368421, "from": "reforma", "to": "MEX - Medios CDMX 2 - TW"}, {"Frecuencia": 23, "value": 0.26136363636363635, "width": 0.26136363636363635, "length": 3.8260869565217392, "from": "reforma", "to": "MEX - Influenciadores de Interés - TW"}, {"Frecuencia": 27, "value": 0.3068181818181818, "width": 0.3068181818181818, "length": 3.259259259259259, "from": "nacional", "to": "MEX - Medios CDMX 2 - TW"}, {"Frecuencia": 10, "value": 0.11363636363636363, "width": 0.11363636363636363, "length": 8.8, "from": "nacional", "to": "MEX - Influenciadores de Interés - TW"}, {"Frecuencia": 30, "value": 0.3409090909090909, "width": 0.3409090909090909, "length": 2.9333333333333336, "from": "paquete", "to": "MEX - Medios CDMX 2 - TW"}, {"Frecuencia": 20, "value": 0.22727272727272727, "width": 0.22727272727272727, "length": 4.4, "from": "carlos", "to": "MEX - Medios CDMX 2 - TW"}, {"Frecuencia": 7, "value": 0.07954545454545454, "width": 0.07954545454545454, "length": 12.571428571428571, "from": "bukele", "to": "MEX - Influenciadores de Interés - TW"}, {"Frecuencia": 24, "value": 0.2727272727272727, "width": 0.2727272727272727, "length": 3.666666666666667, "from": "iniciativas", "to": "MEX - Medios CDMX 2 - TW"}, {"Frecuencia": 16, "value": 0.18181818181818182, "width": 0.18181818181818182, "length": 5.5, "from": "seguridad", "to": "MEX - Medios CDMX 2 - TW"}, {"Frecuencia": 16, "value": 0.18181818181818182, "width": 0.18181818181818182, "length": 5.5, "from": "mundial", "to": "MEX - Medios CDMX 2 - TW"}, {"Frecuencia": 7, "value": 0.07954545454545454, "width": 0.07954545454545454, "length": 12.571428571428571, "from": "constitucionales", "to": "MEX - Influenciadores de Interés - TW"}, {"Frecuencia": 15, "value": 0.17045454545454544, "width": 0.17045454545454544, "length": 5.866666666666667, "from": "palacio", "to": "MEX - Medios CDMX 2 - TW"}, {"Frecuencia": 25, "value": 0.2840909090909091, "width": 0.2840909090909091, "length": 3.5199999999999996, "from": "MEX - Medios CDMX 2 - TW", "to": "completa"}, {"Frecuencia": 18, "value": 0.20454545454545456, "width": 0.20454545454545456, "length": 4.888888888888888, "from": "MEX - Medios CDMX 2 - TW", "to": "estados"}, {"Frecuencia": 17, "value": 0.19318181818181818, "width": 0.19318181818181818, "length": 5.176470588235294, "from": "MEX - Medios CDMX 2 - TW", "to": "acuerdo"}, {"Frecuencia": 16, "value": 0.18181818181818182, "width": 0.18181818181818182, "length": 5.5, "from": "MEX - Medios CDMX 2 - TW", "to": "millones"}, {"Frecuencia": 16, "value": 0.18181818181818182, "width": 0.18181818181818182, "length": 5.5, "from": "MEX - Medios CDMX 2 - TW", "to": "ciudad"}, {"Frecuencia": 15, "value": 0.17045454545454544, "width": 0.17045454545454544, "length": 5.866666666666667, "from": "MEX - Medios CDMX 2 - TW", "to": "pensiones"}, {"Frecuencia": 15, "value": 0.17045454545454544, "width": 0.17045454545454544, "length": 5.866666666666667, "from": "MEX - Medios CDMX 2 - TW", "to": "violencia"}, {"Frecuencia": 15, "value": 0.17045454545454544, "width": 0.17045454545454544, "length": 5.866666666666667, "from": "MEX - Medios CDMX 2 - TW", "to": "electoral"}, {"Frecuencia": 15, "value": 0.17045454545454544, "width": 0.17045454545454544, "length": 5.866666666666667, "from": "MEX - Medios CDMX 2 - TW", "to": "judicial"}, {"Frecuencia": 15, "value": 0.17045454545454544, "width": 0.17045454545454544, "length": 5.866666666666667, "from": "MEX - Medios CDMX 2 - TW", "to": "política"}, {"Frecuencia": 7, "value": 0.07954545454545454, "width": 0.07954545454545454, "length": 12.571428571428571, "from": "electoral", "to": "MEX - Influenciadores de Interés - TW"}, {"Frecuencia": 11, "value": 0.125, "width": 0.125, "length": 8.0, "from": "judicial", "to": "MEX - Influenciadores de Interés - TW"}, {"Frecuencia": 10, "value": 0.11363636363636363, "width": 0.11363636363636363, "length": 8.8, "from": "política", "to": "MEX - Influenciadores de Interés - TW"}, {"Frecuencia": 16, "value": 0.18181818181818182, "width": 0.18181818181818182, "length": 5.5, "from": "MEX - Influenciadores de Interés - TW", "to": "pueblo"}, {"Frecuencia": 9, "value": 0.10227272727272728, "width": 0.10227272727272728, "length": 9.777777777777777, "from": "MEX - Influenciadores de Interés - TW", "to": "elecciones"}, {"Frecuencia": 7, "value": 0.07954545454545454, "width": 0.07954545454545454, "length": 12.571428571428571, "from": "MEX - Influenciadores de Interés - TW", "to": "mayoría"}, {"Frecuencia": 7, "value": 0.07954545454545454, "width": 0.07954545454545454, "length": 12.571428571428571, "from": "MEX - Influenciadores de Interés - TW", "to": "salario"}, {"Frecuencia": 6, "value": 0.06818181818181818, "width": 0.06818181818181818, "length": 14.666666666666668, "from": "MEX - Influenciadores de Interés - TW", "to": "momento"}, {"Frecuencia": 6, "value": 0.06818181818181818, "width": 0.06818181818181818, "length": 14.666666666666668, "from": "MEX - Influenciadores de Interés - TW", "to": "ejecutivo"}, {"Frecuencia": 6, "value": 0.06818181818181818, "width": 0.06818181818181818, "length": 14.666666666666668, "from": "MEX - Influenciadores de Interés - TW", "to": "electorales"}, {"Frecuencia": 6, "value": 0.06818181818181818, "width": 0.06818181818181818, "length": 14.666666666666668, "from": "MEX - Influenciadores de Interés - TW", "to": "políticos"}]], "2024-02-06-2024-02-06": [[{"color": "#97c2fc", "size": 10, "id": "MEX - Influenciadores de Interés 2 - TW", "label": "MEX - Influenciadores de Interés 2 - TW", "shape": "dot", "font": {"color": "white"}}, {"color": "#97c2fc", "size": 10, "id": "presidente", "label": "presidente", "shape": "dot", "font": {"color": "white"}}, {"color": "#97c2fc", "size": 10, "id": "méxico", "label": "méxico", "shape": "dot", "font": {"color": "white"}}, {"color": "#97c2fc", "size": 10, "id": "inglés", "label": "inglés", "shape": "dot", "font": {"color": "white"}}, {"color": "#97c2fc", "size": 10, "id": "gobierno", "label": "gobierno", "shape": "dot", "font": {"color": "white"}}, {"color": "#97c2fc", "size": 10, "id": "reformas", "label": "reformas", "shape": "dot", "font": {"color": "white"}}, {"color": "#97c2fc", "size": 10, "id": "contra", "label": "contra", "shape": "dot", "font": {"color": "white"}}, {"color": "#97c2fc", "size": 10, "id": "gracias", "label": "gracias", "shape": "dot", "font": {"color": "white"}}, {"color": "#97c2fc", "size": 10, "id": "obrador", "label": "obrador", "shape": "dot", "font": {"color": "white"}}, {"color": "#97c2fc", "size": 10, "id": "también", "label": "también", "shape": "dot", "font": {"color": "white"}}, {"color": "#97c2fc", "size": 10, "id": "iniciativas", "label": "iniciativas", "shape": "dot", "font": {"color": "white"}}, {"color": "#97c2fc", "size": 10, "id": "porque", "label": "porque", "shape": "dot", "font": {"color": "white"}}, {"color": "#97c2fc", "size": 10, "id": "quiere", "label": "quiere", "shape": "dot", "font": {"color": "white"}}, {"color": "#97c2fc", "size": 10, "id": "hablar", "label": "hablar", "shape": "dot", "font": {"color": "white"}}, {"color": "#97c2fc", "size": 10, "id": "constitución", "label": "constitución", "shape": "dot", "font": {"color": "white"}}, {"color": "#97c2fc", "size": 10, "id": "xóchitl", "label": "xóchitl", "shape": "dot", "font": {"color": "white"}}, {"color": "#97c2fc", "size": 10, "id": "campaña", "label": "campaña", "shape": "dot", "font": {"color": "white"}}, {"color": "#97c2fc", "size": 10, "id": "periodista", "label": "periodista", "shape": "dot", "font": {"color": "white"}}, {"color": "#97c2fc", "size": 10, "id": "cuando", "label": "cuando", "shape": "dot", "font": {"color": "white"}}, {"color": "#97c2fc", "size": 10, "id": "morena", "label": "morena", "shape": "dot", "font": {"color": "white"}}, {"color": "#97c2fc", "size": 10, "id": "inseguridad", "label": "inseguridad", "shape": "dot", "font": {"color": "white"}}, {"color": "#97c2fc", "size": 10, "id": "paquete", "label": "paquete", "shape": "dot", "font": {"color": "white"}}, {"color": "#97c2fc", "size": 10, "id": "durante", "label": "durante", "shape": "dot", "font": {"color": "white"}}, {"color": "#97c2fc", "size": 10, "id": "nacional", "label": "nacional", "shape": "dot", "font": {"color": "white"}}, {"color": "#97c2fc", "size": 10, "id": "estados", "label": "estados", "shape": "dot", "font": {"color": "white"}}, {"color": "#97c2fc", "size": 10, "id": "andrés", "label": "andrés", "shape": "dot", "font": {"color": "white"}}, {"color": "#97c2fc", "size": 10, "id": "manuel", "label": "manuel", "shape": "dot", "font": {"color": "white"}}, {"color": "#97c2fc", "size": 10, "id": "mañana", "label": "mañana", "shape": "dot", "font": {"color": "white"}}, {"color": "#97c2fc", "size": 10, "id": "zócalo", "label": "zócalo", "shape": "dot", "font": {"color": "white"}}, {"color": "#97c2fc", "size": 10, "id": "tiempo", "label": "tiempo", "shape": "dot", "font": {"color": "white"}}, {"color": "#97c2fc", "size": 10, "id": "además", "label": "además", "shape": "dot", "font": {"color": "white"}}, {"color": "#97c2fc", "size": 10, "id": "MEX - Medios CDMX - TW", "label": "MEX - Medios CDMX - TW", "shape": "dot", "font": {"color": "white"}}, {"color": "#97c2fc", "size": 10, "id": "MEX - Medios CDMX 2 - TW", "label": "MEX - Medios CDMX 2 - TW", "shape": "dot", "font": {"color": "white"}}, {"color": "#97c2fc", "size": 10, "id": "MEX - Influenciadores de Interés - TW", "label": "MEX - Influenciadores de Interés - TW", "shape": "dot", "font": {"color": "white"}}, {"color": "#97c2fc", "size": 10, "id": "reforma", "label": "reforma", "shape": "dot", "font": {"color": "white"}}, {"color": "#97c2fc", "size": 10, "id": "carlos", "label": "carlos", "shape": "dot", "font": {"color": "white"}}, {"color": "#97c2fc", "size": 10, "id": "piñera", "label": "piñera", "shape": "dot", "font": {"color": "white"}}, {"color": "#97c2fc", "size": 10, "id": "iniciativa", "label": "iniciativa", "shape": "dot", "font": {"color": "white"}}, {"color": "#97c2fc", "size": 10, "id": "febrero", "label": "febrero", "shape": "dot", "font": {"color": "white"}}, {"color": "#97c2fc", "size": 10, "id": "escribe", "label": "escribe", "shape": "dot", "font": {"color": "white"}}, {"color": "#97c2fc", "size": 10, "id": "detalles", "label": "detalles", "shape": "dot", "font": {"color": "white"}}, {"color": "#97c2fc", "size": 10, "id": "cáncer", "label": "cáncer", "shape": "dot", "font": {"color": "white"}}, {"color": "#97c2fc", "size": 10, "id": "electoral", "label": "electoral", "shape": "dot", "font": {"color": "white"}}, {"color": "#97c2fc", "size": 10, "id": "expresidente", "label": "expresidente", "shape": "dot", "font": {"color": "white"}}, {"color": "#97c2fc", "size": 10, "id": "sebastián", "label": "sebastián", "shape": "dot", "font": {"color": "white"}}, {"color": "#97c2fc", "size": 10, "id": "martes", "label": "martes", "shape": "dot", "font": {"color": "white"}}, {"color": "#97c2fc", "size": 10, "id": "estado", "label": "estado", "shape": "dot", "font": {"color": "white"}}, {"color": "#97c2fc", "size": 10, "id": "pensiones", "label": "pensiones", "shape": "dot", "font": {"color": "white"}}, {"color": "#97c2fc", "size": 10, "id": "personas", "label": "personas", "shape": "dot", "font": {"color": "white"}}, {"color": "#97c2fc", "size": 10, "id": "seguridad", "label": "seguridad", "shape": "dot", "font": {"color": "white"}}, {"color": "#97c2fc", "size": 10, "id": "accidente", "label": "accidente", "shape": "dot", "font": {"color": "white"}}, {"color": "#97c2fc", "size": 10, "id": "historia", "label": "historia", "shape": "dot", "font": {"color": "white"}}, {"color": "#97c2fc", "size": 10, "id": "millones", "label": "millones", "shape": "dot", "font": {"color": "white"}}, {"color": "#97c2fc", "size": 10, "id": "presidencial", "label": "presidencial", "shape": "dot", "font": {"color": "white"}}, {"color": "#97c2fc", "size": 10, "id": "elecciones", "label": "elecciones", "shape": "dot", "font": {"color": "white"}}, {"color": "#97c2fc", "size": 10, "id": "helicóptero", "label": "helicóptero", "shape": "dot", "font": {"color": "white"}}, {"color": "#97c2fc", "size": 10, "id": "completa", "label": "completa", "shape": "dot", "font": {"color": "white"}}, {"color": "#97c2fc", "size": 10, "id": "judicial", "label": "judicial", "shape": "dot", "font": {"color": "white"}}, {"color": "#97c2fc", "size": 10, "id": "constitucionales", "label": "constitucionales", "shape": "dot", "font": {"color": "white"}}, {"color": "#97c2fc", "size": 10, "id": "opinión", "label": "opinión", "shape": "dot", "font": {"color": "white"}}, {"color": "#97c2fc", "size": 10, "id": "prohibir", "label": "prohibir", "shape": "dot", "font": {"color": "white"}}, {"color": "#97c2fc", "size": 10, "id": "oposición", "label": "oposición", "shape": "dot", "font": {"color": "white"}}, {"color": "#97c2fc", "size": 10, "id": "mexicanos", "label": "mexicanos", "shape": "dot", "font": {"color": "white"}}, {"color": "#97c2fc", "size": 10, "id": "candidato", "label": "candidato", "shape": "dot", "font": {"color": "white"}}, {"color": "#97c2fc", "size": 10, "id": "democracia", "label": "democracia", "shape": "dot", "font": {"color": "white"}}, {"color": "#97c2fc", "size": 10, "id": "propuestas", "label": "propuestas", "shape": "dot", "font": {"color": "white"}}, {"color": "#97c2fc", "size": 10, "id": "violencia", "label": "violencia", "shape": "dot", "font": {"color": "white"}}, {"color": "#97c2fc", "size": 10, "id": "máximo", "label": "máximo", "shape": "dot", "font": {"color": "white"}}, {"color": "#97c2fc", "size": 10, "id": "presentó", "label": "presentó", "shape": "dot", "font": {"color": "white"}}, {"color": "#97c2fc", "size": 10, "id": "claudia", "label": "claudia", "shape": "dot", "font": {"color": "white"}}, {"color": "#97c2fc", "size": 10, "id": "realidad", "label": "realidad", "shape": "dot", "font": {"color": "white"}}, {"color": "#97c2fc", "size": 10, "id": "plantear", "label": "plantear", "shape": "dot", "font": {"color": "white"}}], [{"Frecuencia": 31, "value": 0.2818181818181818, "width": 0.2818181818181818, "length": 3.548387096774194, "from": "MEX - Influenciadores de Interés 2 - TW", "to": "presidente"}, {"Frecuencia": 20, "value": 0.18181818181818182, "width": 0.18181818181818182, "length": 5.5, "from": "MEX - Influenciadores de Interés 2 - TW", "to": "méxico"}, {"Frecuencia": 17, "value": 0.15454545454545454, "width": 0.15454545454545454, "length": 6.470588235294118, "from": "MEX - Influenciadores de Interés 2 - TW", "to": "inglés"}, {"Frecuencia": 15, "value": 0.13636363636363635, "width": 0.13636363636363635, "length": 7.333333333333334, "from": "MEX - Influenciadores de Interés 2 - TW", "to": "gobierno"}, {"Frecuencia": 15, "value": 0.13636363636363635, "width": 0.13636363636363635, "length": 7.333333333333334, "from": "MEX - Influenciadores de Interés 2 - TW", "to": "reformas"}, {"Frecuencia": 14, "value": 0.12727272727272726, "width": 0.12727272727272726, "length": 7.857142857142858, "from": "MEX - Influenciadores de Interés 2 - TW", "to": "contra"}, {"Frecuencia": 12, "value": 0.10909090909090909, "width": 0.10909090909090909, "length": 9.166666666666668, "from": "MEX - Influenciadores de Interés 2 - TW", "to": "gracias"}, {"Frecuencia": 12, "value": 0.10909090909090909, "width": 0.10909090909090909, "length": 9.166666666666668, "from": "MEX - Influenciadores de Interés 2 - TW", "to": "obrador"}, {"Frecuencia": 10, "value": 0.09090909090909091, "width": 0.09090909090909091, "length": 11.0, "from": "MEX - Influenciadores de Interés 2 - TW", "to": "también"}, {"Frecuencia": 9, "value": 0.08181818181818182, "width": 0.08181818181818182, "length": 12.222222222222221, "from": "MEX - Influenciadores de Interés 2 - TW", "to": "iniciativas"}, {"Frecuencia": 9, "value": 0.08181818181818182, "width": 0.08181818181818182, "length": 12.222222222222221, "from": "MEX - Influenciadores de Interés 2 - TW", "to": "porque"}, {"Frecuencia": 8, "value": 0.07272727272727272, "width": 0.07272727272727272, "length": 13.75, "from": "MEX - Influenciadores de Interés 2 - TW", "to": "quiere"}, {"Frecuencia": 8, "value": 0.07272727272727272, "width": 0.07272727272727272, "length": 13.75, "from": "MEX - Influenciadores de Interés 2 - TW", "to": "hablar"}, {"Frecuencia": 8, "value": 0.07272727272727272, "width": 0.07272727272727272, "length": 13.75, "from": "MEX - Influenciadores de Interés 2 - TW", "to": "constitución"}, {"Frecuencia": 8, "value": 0.07272727272727272, "width": 0.07272727272727272, "length": 13.75, "from": "MEX - Influenciadores de Interés 2 - TW", "to": "xóchitl"}, {"Frecuencia": 7, "value": 0.06363636363636363, "width": 0.06363636363636363, "length": 15.714285714285715, "from": "MEX - Influenciadores de Interés 2 - TW", "to": "campaña"}, {"Frecuencia": 7, "value": 0.06363636363636363, "width": 0.06363636363636363, "length": 15.714285714285715, "from": "MEX - Influenciadores de Interés 2 - TW", "to": "periodista"}, {"Frecuencia": 6, "value": 0.05454545454545454, "width": 0.05454545454545454, "length": 18.333333333333336, "from": "MEX - Influenciadores de Interés 2 - TW", "to": "cuando"}, {"Frecuencia": 6, "value": 0.05454545454545454, "width": 0.05454545454545454, "length": 18.333333333333336, "from": "MEX - Influenciadores de Interés 2 - TW", "to": "morena"}, {"Frecuencia": 6, "value": 0.05454545454545454, "width": 0.05454545454545454, "length": 18.333333333333336, "from": "MEX - Influenciadores de Interés 2 - TW", "to": "inseguridad"}, {"Frecuencia": 6, "value": 0.05454545454545454, "width": 0.05454545454545454, "length": 18.333333333333336, "from": "MEX - Influenciadores de Interés 2 - TW", "to": "paquete"}, {"Frecuencia": 6, "value": 0.05454545454545454, "width": 0.05454545454545454, "length": 18.333333333333336, "from": "MEX - Influenciadores de Interés 2 - TW", "to": "durante"}, {"Frecuencia": 6, "value": 0.05454545454545454, "width": 0.05454545454545454, "length": 18.333333333333336, "from": "MEX - Influenciadores de Interés 2 - TW", "to": "nacional"}, {"Frecuencia": 6, "value": 0.05454545454545454, "width": 0.05454545454545454, "length": 18.333333333333336, "from": "MEX - Influenciadores de Interés 2 - TW", "to": "estados"}, {"Frecuencia": 6, "value": 0.05454545454545454, "width": 0.05454545454545454, "length": 18.333333333333336, "from": "MEX - Influenciadores de Interés 2 - TW", "to": "andrés"}, {"Frecuencia": 6, "value": 0.05454545454545454, "width": 0.05454545454545454, "length": 18.333333333333336, "from": "MEX - Influenciadores de Interés 2 - TW", "to": "manuel"}, {"Frecuencia": 5, "value": 0.045454545454545456, "width": 0.045454545454545456, "length": 22.0, "from": "MEX - Influenciadores de Interés 2 - TW", "to": "mañana"}, {"Frecuencia": 5, "value": 0.045454545454545456, "width": 0.045454545454545456, "length": 22.0, "from": "MEX - Influenciadores de Interés 2 - TW", "to": "zócalo"}, {"Frecuencia": 5, "value": 0.045454545454545456, "width": 0.045454545454545456, "length": 22.0, "from": "MEX - Influenciadores de Interés 2 - TW", "to": "tiempo"}, {"Frecuencia": 5, "value": 0.045454545454545456, "width": 0.045454545454545456, "length": 22.0, "from": "MEX - Influenciadores de Interés 2 - TW", "to": "además"}, {"Frecuencia": 110, "value": 1.0, "width": 1.0, "length": 1.0, "from": "presidente", "to": "MEX - Medios CDMX - TW"}, {"Frecuencia": 69, "value": 0.6272727272727273, "width": 0.6272727272727273, "length": 1.5942028985507246, "from": "presidente", "to": "MEX - Medios CDMX 2 - TW"}, {"Frecuencia": 31, "value": 0.2818181818181818, "width": 0.2818181818181818, "length": 3.548387096774194, "from": "presidente", "to": "MEX - Influenciadores de Interés - TW"}, {"Frecuencia": 77, "value": 0.7, "width": 0.7, "length": 1.4285714285714286, "from": "méxico", "to": "MEX - Medios CDMX - TW"}, {"Frecuencia": 35, "value": 0.3181818181818182, "width": 0.3181818181818182, "length": 3.142857142857143, "from": "méxico", "to": "MEX - Medios CDMX 2 - TW"}, {"Frecuencia": 11, "value": 0.1, "width": 0.1, "length": 10.0, "from": "méxico", "to": "MEX - Influenciadores de Interés - TW"}, {"Frecuencia": 32, "value": 0.2909090909090909, "width": 0.2909090909090909, "length": 3.4375, "from": "gobierno", "to": "MEX - Medios CDMX - TW"}, {"Frecuencia": 21, "value": 0.19090909090909092, "width": 0.19090909090909092, "length": 5.238095238095238, "from": "gobierno", "to": "MEX - Medios CDMX 2 - TW"}, {"Frecuencia": 12, "value": 0.10909090909090909, "width": 0.10909090909090909, "length": 9.166666666666668, "from": "gobierno", "to": "MEX - Influenciadores de Interés - TW"}, {"Frecuencia": 72, "value": 0.6545454545454545, "width": 0.6545454545454545, "length": 1.5277777777777777, "from": "reformas", "to": "MEX - Medios CDMX - TW"}, {"Frecuencia": 52, "value": 0.4727272727272727, "width": 0.4727272727272727, "length": 2.1153846153846154, "from": "reformas", "to": "MEX - Medios CDMX 2 - TW"}, {"Frecuencia": 12, "value": 0.10909090909090909, "width": 0.10909090909090909, "length": 9.166666666666668, "from": "reformas", "to": "MEX - Influenciadores de Interés - TW"}, {"Frecuencia": 42, "value": 0.38181818181818183, "width": 0.38181818181818183, "length": 2.619047619047619, "from": "contra", "to": "MEX - Medios CDMX - TW"}, {"Frecuencia": 26, "value": 0.23636363636363636, "width": 0.23636363636363636, "length": 4.230769230769231, "from": "contra", "to": "MEX - Medios CDMX 2 - TW"}, {"Frecuencia": 7, "value": 0.06363636363636363, "width": 0.06363636363636363, "length": 15.714285714285715, "from": "gracias", "to": "MEX - Influenciadores de Interés - TW"}, {"Frecuencia": 28, "value": 0.2545454545454545, "width": 0.2545454545454545, "length": 3.928571428571429, "from": "obrador", "to": "MEX - Medios CDMX - TW"}, {"Frecuencia": 32, "value": 0.2909090909090909, "width": 0.2909090909090909, "length": 3.4375, "from": "obrador", "to": "MEX - Medios CDMX 2 - TW"}, {"Frecuencia": 5, "value": 0.045454545454545456, "width": 0.045454545454545456, "length": 22.0, "from": "obrador", "to": "MEX - Influenciadores de Interés - TW"}, {"Frecuencia": 11, "value": 0.1, "width": 0.1, "length": 10.0, "from": "también", "to": "MEX - Influenciadores de Interés - TW"}, {"Frecuencia": 34, "value": 0.3090909090909091, "width": 0.3090909090909091, "length": 3.235294117647059, "from": "iniciativas", "to": "MEX - Medios CDMX - TW"}, {"Frecuencia": 27, "value": 0.24545454545454545, "width": 0.24545454545454545, "length": 4.074074074074074, "from": "iniciativas", "to": "MEX - Medios CDMX 2 - TW"}, {"Frecuencia": 13, "value": 0.11818181818181818, "width": 0.11818181818181818, "length": 8.461538461538462, "from": "iniciativas", "to": "MEX - Influenciadores de Interés - TW"}, {"Frecuencia": 8, "value": 0.07272727272727272, "width": 0.07272727272727272, "length": 13.75, "from": "porque", "to": "MEX - Influenciadores de Interés - TW"}, {"Frecuencia": 6, "value": 0.05454545454545454, "width": 0.05454545454545454, "length": 18.333333333333336, "from": "quiere", "to": "MEX - Influenciadores de Interés - TW"}, {"Frecuencia": 28, "value": 0.2545454545454545, "width": 0.2545454545454545, "length": 3.928571428571429, "from": "constitución", "to": "MEX - Medios CDMX - TW"}, {"Frecuencia": 21, "value": 0.19090909090909092, "width": 0.19090909090909092, "length": 5.238095238095238, "from": "constitución", "to": "MEX - Medios CDMX 2 - TW"}, {"Frecuencia": 17, "value": 0.15454545454545454, "width": 0.15454545454545454, "length": 6.470588235294118, "from": "xóchitl", "to": "MEX - Medios CDMX 2 - TW"}, {"Frecuencia": 14, "value": 0.12727272727272726, "width": 0.12727272727272726, "length": 7.857142857142858, "from": "campaña", "to": "MEX - Medios CDMX 2 - TW"}, {"Frecuencia": 7, "value": 0.06363636363636363, "width": 0.06363636363636363, "length": 15.714285714285715, "from": "campaña", "to": "MEX - Influenciadores de Interés - TW"}, {"Frecuencia": 30, "value": 0.2727272727272727, "width": 0.2727272727272727, "length": 3.666666666666667, "from": "paquete", "to": "MEX - Medios CDMX - TW"}, {"Frecuencia": 15, "value": 0.13636363636363635, "width": 0.13636363636363635, "length": 7.333333333333334, "from": "paquete", "to": "MEX - Medios CDMX 2 - TW"}, {"Frecuencia": 22, "value": 0.2, "width": 0.2, "length": 5.0, "from": "durante", "to": "MEX - Medios CDMX - TW"}, {"Frecuencia": 30, "value": 0.2727272727272727, "width": 0.2727272727272727, "length": 3.666666666666667, "from": "nacional", "to": "MEX - Medios CDMX - TW"}, {"Frecuencia": 20, "value": 0.18181818181818182, "width": 0.18181818181818182, "length": 5.5, "from": "nacional", "to": "MEX - Medios CDMX 2 - TW"}, {"Frecuencia": 14, "value": 0.12727272727272726, "width": 0.12727272727272726, "length": 7.857142857142858, "from": "estados", "to": "MEX - Medios CDMX 2 - TW"}, {"Frecuencia": 5, "value": 0.045454545454545456, "width": 0.045454545454545456, "length": 22.0, "from": "zócalo", "to": "MEX - Influenciadores de Interés - TW"}, {"Frecuencia": 48, "value": 0.43636363636363634, "width": 0.43636363636363634, "length": 2.291666666666667, "from": "MEX - Medios CDMX - TW", "to": "reforma"}, {"Frecuencia": 41, "value": 0.37272727272727274, "width": 0.37272727272727274, "length": 2.6829268292682924, "from": "MEX - Medios CDMX - TW", "to": "carlos"}, {"Frecuencia": 40, "value": 0.36363636363636365, "width": 0.36363636363636365, "length": 2.75, "from": "MEX - Medios CDMX - TW", "to": "piñera"}, {"Frecuencia": 39, "value": 0.35454545454545455, "width": 0.35454545454545455, "length": 2.8205128205128203, "from": "MEX - Medios CDMX - TW", "to": "iniciativa"}, {"Frecuencia": 39, "value": 0.35454545454545455, "width": 0.35454545454545455, "length": 2.8205128205128203, "from": "MEX - Medios CDMX - TW", "to": "febrero"}, {"Frecuencia": 38, "value": 0.34545454545454546, "width": 0.34545454545454546, "length": 2.8947368421052633, "from": "MEX - Medios CDMX - TW", "to": "escribe"}, {"Frecuencia": 35, "value": 0.3181818181818182, "width": 0.3181818181818182, "length": 3.142857142857143, "from": "MEX - Medios CDMX - TW", "to": "detalles"}, {"Frecuencia": 35, "value": 0.3181818181818182, "width": 0.3181818181818182, "length": 3.142857142857143, "from": "MEX - Medios CDMX - TW", "to": "cáncer"}, {"Frecuencia": 33, "value": 0.3, "width": 0.3, "length": 3.3333333333333335, "from": "MEX - Medios CDMX - TW", "to": "electoral"}, {"Frecuencia": 33, "value": 0.3, "width": 0.3, "length": 3.3333333333333335, "from": "MEX - Medios CDMX - TW", "to": "expresidente"}, {"Frecuencia": 32, "value": 0.2909090909090909, "width": 0.2909090909090909, "length": 3.4375, "from": "MEX - Medios CDMX - TW", "to": "sebastián"}, {"Frecuencia": 31, "value": 0.2818181818181818, "width": 0.2818181818181818, "length": 3.548387096774194, "from": "MEX - Medios CDMX - TW", "to": "martes"}, {"Frecuencia": 28, "value": 0.2545454545454545, "width": 0.2545454545454545, "length": 3.928571428571429, "from": "MEX - Medios CDMX - TW", "to": "estado"}, {"Frecuencia": 26, "value": 0.23636363636363636, "width": 0.23636363636363636, "length": 4.230769230769231, "from": "MEX - Medios CDMX - TW", "to": "pensiones"}, {"Frecuencia": 23, "value": 0.20909090909090908, "width": 0.20909090909090908, "length": 4.782608695652174, "from": "MEX - Medios CDMX - TW", "to": "personas"}, {"Frecuencia": 23, "value": 0.20909090909090908, "width": 0.20909090909090908, "length": 4.782608695652174, "from": "MEX - Medios CDMX - TW", "to": "seguridad"}, {"Frecuencia": 23, "value": 0.20909090909090908, "width": 0.20909090909090908, "length": 4.782608695652174, "from": "MEX - Medios CDMX - TW", "to": "accidente"}, {"Frecuencia": 23, "value": 0.20909090909090908, "width": 0.20909090909090908, "length": 4.782608695652174, "from": "MEX - Medios CDMX - TW", "to": "historia"}, {"Frecuencia": 21, "value": 0.19090909090909092, "width": 0.19090909090909092, "length": 5.238095238095238, "from": "MEX - Medios CDMX - TW", "to": "millones"}, {"Frecuencia": 28, "value": 0.2545454545454545, "width": 0.2545454545454545, "length": 3.928571428571429, "from": "reforma", "to": "MEX - Medios CDMX 2 - TW"}, {"Frecuencia": 5, "value": 0.045454545454545456, "width": 0.045454545454545456, "length": 22.0, "from": "reforma", "to": "MEX - Influenciadores de Interés - TW"}, {"Frecuencia": 18, "value": 0.16363636363636364, "width": 0.16363636363636364, "length": 6.111111111111111, "from": "carlos", "to": "MEX - Medios CDMX 2 - TW"}, {"Frecuencia": 17, "value": 0.15454545454545454, "width": 0.15454545454545454, "length": 6.470588235294118, "from": "piñera", "to": "MEX - Medios CDMX 2 - TW"}, {"Frecuencia": 16, "value": 0.14545454545454545, "width": 0.14545454545454545, "length": 6.875, "from": "febrero", "to": "MEX - Medios CDMX 2 - TW"}, {"Frecuencia": 17, "value": 0.15454545454545454, "width": 0.15454545454545454, "length": 6.470588235294118, "from": "electoral", "to": "MEX - Medios CDMX 2 - TW"}, {"Frecuencia": 6, "value": 0.05454545454545454, "width": 0.05454545454545454, "length": 18.333333333333336, "from": "electoral", "to": "MEX - Influenciadores de Interés - TW"}, {"Frecuencia": 16, "value": 0.14545454545454545, "width": 0.14545454545454545, "length": 6.875, "from": "expresidente", "to": "MEX - Medios CDMX 2 - TW"}, {"Frecuencia": 15, "value": 0.13636363636363635, "width": 0.13636363636363635, "length": 7.333333333333334, "from": "sebastián", "to": "MEX - Medios CDMX 2 - TW"}, {"Frecuencia": 8, "value": 0.07272727272727272, "width": 0.07272727272727272, "length": 13.75, "from": "martes", "to": "MEX - Influenciadores de Interés - TW"}, {"Frecuencia": 13, "value": 0.11818181818181818, "width": 0.11818181818181818, "length": 8.461538461538462, "from": "pensiones", "to": "MEX - Medios CDMX 2 - TW"}, {"Frecuencia": 13, "value": 0.11818181818181818, "width": 0.11818181818181818, "length": 8.461538461538462, "from": "personas", "to": "MEX - Medios CDMX 2 - TW"}, {"Frecuencia": 7, "value": 0.06363636363636363, "width": 0.06363636363636363, "length": 15.714285714285715, "from": "personas", "to": "MEX - Influenciadores de Interés - TW"}, {"Frecuencia": 17, "value": 0.15454545454545454, "width": 0.15454545454545454, "length": 6.470588235294118, "from": "seguridad", "to": "MEX - Medios CDMX 2 - TW"}, {"Frecuencia": 19, "value": 0.17272727272727273, "width": 0.17272727272727273, "length": 5.7894736842105265, "from": "MEX - Medios CDMX 2 - TW", "to": "presidencial"}, {"Frecuencia": 17, "value": 0.15454545454545454, "width": 0.15454545454545454, "length": 6.470588235294118, "from": "MEX - Medios CDMX 2 - TW", "to": "elecciones"}, {"Frecuencia": 17, "value": 0.15454545454545454, "width": 0.15454545454545454, "length": 6.470588235294118, "from": "MEX - Medios CDMX 2 - TW", "to": "helicóptero"}, {"Frecuencia": 16, "value": 0.14545454545454545, "width": 0.14545454545454545, "length": 6.875, "from": "MEX - Medios CDMX 2 - TW", "to": "completa"}, {"Frecuencia": 15, "value": 0.13636363636363635, "width": 0.13636363636363635, "length": 7.333333333333334, "from": "MEX - Medios CDMX 2 - TW", "to": "judicial"}, {"Frecuencia": 14, "value": 0.12727272727272726, "width": 0.12727272727272726, "length": 7.857142857142858, "from": "MEX - Medios CDMX 2 - TW", "to": "constitucionales"}, {"Frecuencia": 14, "value": 0.12727272727272726, "width": 0.12727272727272726, "length": 7.857142857142858, "from": "MEX - Medios CDMX 2 - TW", "to": "opinión"}, {"Frecuencia": 9, "value": 0.08181818181818182, "width": 0.08181818181818182, "length": 12.222222222222221, "from": "completa", "to": "MEX - Influenciadores de Interés - TW"}, {"Frecuencia": 5, "value": 0.045454545454545456, "width": 0.045454545454545456, "length": 22.0, "from": "constitucionales", "to": "MEX - Influenciadores de Interés - TW"}, {"Frecuencia": 21, "value": 0.19090909090909092, "width": 0.19090909090909092, "length": 5.238095238095238, "from": "MEX - Influenciadores de Interés - TW", "to": "prohibir"}, {"Frecuencia": 9, "value": 0.08181818181818182, "width": 0.08181818181818182, "length": 12.222222222222221, "from": "MEX - Influenciadores de Interés - TW", "to": "oposición"}, {"Frecuencia": 9, "value": 0.08181818181818182, "width": 0.08181818181818182, "length": 12.222222222222221, "from": "MEX - Influenciadores de Interés - TW", "to": "mexicanos"}, {"Frecuencia": 9, "value": 0.08181818181818182, "width": 0.08181818181818182, "length": 12.222222222222221, "from": "MEX - Influenciadores de Interés - TW", "to": "candidato"}, {"Frecuencia": 8, "value": 0.07272727272727272, "width": 0.07272727272727272, "length": 13.75, "from": "MEX - Influenciadores de Interés - TW", "to": "democracia"}, {"Frecuencia": 7, "value": 0.06363636363636363, "width": 0.06363636363636363, "length": 15.714285714285715, "from": "MEX - Influenciadores de Interés - TW", "to": "propuestas"}, {"Frecuencia": 7, "value": 0.06363636363636363, "width": 0.06363636363636363, "length": 15.714285714285715, "from": "MEX - Influenciadores de Interés - TW", "to": "violencia"}, {"Frecuencia": 6, "value": 0.05454545454545454, "width": 0.05454545454545454, "length": 18.333333333333336, "from": "MEX - Influenciadores de Interés - TW", "to": "máximo"}, {"Frecuencia": 6, "value": 0.05454545454545454, "width": 0.05454545454545454, "length": 18.333333333333336, "from": "MEX - Influenciadores de Interés - TW", "to": "presentó"}, {"Frecuencia": 6, "value": 0.05454545454545454, "width": 0.05454545454545454, "length": 18.333333333333336, "from": "MEX - Influenciadores de Interés - TW", "to": "claudia"}, {"Frecuencia": 5, "value": 0.045454545454545456, "width": 0.045454545454545456, "length": 22.0, "from": "MEX - Influenciadores de Interés - TW", "to": "realidad"}, {"Frecuencia": 5, "value": 0.045454545454545456, "width": 0.045454545454545456, "length": 22.0, "from": "MEX - Influenciadores de Interés - TW", "to": "plantear"}]]}